Workbook

Sheet Synthèse
A1: ALQAVYA — Synthèse du modèle de coûts et de prix
A3: Indicateur | B3: FCFA | C3: EUR
A4: Investissement immobilier maison mère Yaoundé | B4: ='Maison mère Yaoundé'!$E$24 -> 4.0776709e+08 | C4: =B4/Hypothèses!$C$6 -> 621636.93
A5: Équipements importés (coût rendu) | B5: ='Équipements importés'!$M$24 -> 80813184 | C5: =B5/Hypothèses!$C$6 -> 123198.9
A6: Flotte | B6: =Flotte!$D$7 -> 33537700 | C6: =B6/Hypothèses!$C$6 -> 51127.894
A7: INVESTISSEMENT TOTAL MAISON MÈRE | B7: =B4+B5+B6 -> 5.2211798e+08 | C7: =B7/Hypothèses!$C$6 -> 795963.73
A8: Fonctionnement Cameroun / mois | B8: =Fonctionnement!$B$12 -> 11105852 | C8: =B8/Hypothèses!$C$6 -> 16930.763
A9: Amortissements / mois | B9: =Fonctionnement!$B$24 -> 3333033.4 | C9: =B9/Hypothèses!$C$6 -> 5081.1767
A10: Siège France / mois | B10: =Fonctionnement!$B$31 -> 10038610 | C10: =B10/Hypothèses!$C$6 -> 15303.762
A11: Coût de revient d'une livraison | B11: =Prix!$B$11 -> 1512.0138 | C11: =B11/Hypothèses!$C$6 -> 2.3050502
A12: Prix plancher TTC d'une livraison | B12: =Prix!$B$13 -> 2163.6918 | C12: =B12/Hypothèses!$C$6 -> 3.2985269
A13: Coût d'une heure de studio | B13: =Prix!$B$24 -> 17135.478 | C13: =B13/Hypothèses!$C$6 -> 26.122868
A14: Seuil filiale seule (commandes / mois) | B14: =Prix!$B$55 -> 3449.3629
A15: Seuil groupe après impôts (commandes / mois) | B15: =Prix!$B$56 -> 8746.0828
A18: Méthode : chaque prix d'entrée provient d'une source publiée (feuilles Hypothèses et Sources) ; surfaces, effectifs, volumes, durées et marge sont des hypothèses modifiables (cellules bleues). Postes sans source publique (assurances, entretien, caméras, parking, VRD, transport du conteneur, marketing) : provisions à chiffrer sur devis, non incluses.

Sheet Hypothèses
A1: ALQAVYA — Hypothèses et données sourcées (cellules bleues = entrées modifiables)
A2: Légende : bleu = entrée ; noir = formule ; vert = lien vers une autre feuille ; jaune = levier clé. Type « Source » = chiffre publié (URL) ; « Hypothèse » = choix de dimensionnement ou de gestion, à ajuster.
A4: ID | B4: Libellé | C4: Valeur retenue | D4: Unité | E4: Bas | F4: Haut | G4: Type | H4: Règle | I4: Source | J4: URL
A5: Change
A6: fx | B6: Parité fixe EUR → FCFA | C6: 655.957 | D6: FCFA / EUR | E6: 655.957 | F6: 655.957 | G6: Source | I6: Parité fixe du franc CFA (BEAC) (confiance : high) | J6: https://www.beac.int
A7: tva_fr | B7: TVA française (achats exportés hors UE facturés HT) | C7: 0.2 | D7: % | E7: 0.2 | F7: 0.2 | G7: Source | I7: Taux normal de TVA en France (confiance : high) | J7: https://www.service-public.fr/professionnels-entreprises/vosdroits/F23567
A8: Fiscalité Cameroun
A9: is_cm | B9: IS Cameroun, CA ≤ 3 Md FCFA (CAC compris) | C9: 0.275 | D9: % | E9: 0.275 | F9: 0.275 | G9: Source | H9: milieu | I9: DGI Cameroun : Fiche technique A/s Impôt sur les Sociétés (IS) (confiance : high) | J9: https://www.impots.cm/sites/default/files/documents/ok%20FT%20IS%20ok.pdf
A10: min_perc | B10: Minimum de perception (acompte IS, dû même en perte) | C10: 0.022 | D10: % | E10: 0.022 | F10: 0.022 | G10: Source | H10: milieu | I10: DGI Cameroun : Fiche technique IS ; LeFisk (commentaire de la fiche DGI) (confiance : medium) | J10: https://www.impots.cm/sites/default/files/documents/ok%20FT%20IS%20ok.pdf
A11: patente | B11: Patente (moyennes entreprises), % du CA, dès l'an 2 (principal seul) | C11: 0.00283 | D11: % | E11: 0.00283 | F11: 0.00283 | G11: Source | H11: milieu | I11: Deloitte Avocats : Cameroun, brèves juridiques et fiscales 1er trimestre 2017 (confiance : medium) | J11: https://blog.avocats.deloitte.fr/cameroun-breves-juridiques-fiscales-1er-trimestre-2017/
A12: tva_cm | B12: TVA Cameroun (17,5 % + CAC) | C12: 0.1925 | D12: % | E12: 0.1925 | F12: 0.1925 | G12: Source | H12: milieu | I12: DGI Cameroun : Fiche TVA (confiance : high) | J12: https://impots.cm/sites/default/files/documents/FICHE%20TVA.pdf
A13: conv_div | B13: Retenue dividendes vers la France (plafond conventionnel) | C13: 0.15 | D13: % | E13: 0.15 | F13: 0.15 | G13: Source | H13: milieu | I13: Sénat : rapport n° 37 (1995-1996) sur l'avenant à la convention fiscale du 21 octobre 1976 (confiance : high) | J13: https://www.senat.fr/rap/l95-037/l95-0371.html
A14: ircm_pme | B14: IRCM dividendes PME (hors CAC ; éligibilité à confirmer) | C14: 0.1 | D14: % | E14: 0.1 | F14: 0.1 | G14: Source | H14: milieu | I14: MINFI : Exposé des mesures fiscales, lancement du budget 2025 (confiance : medium) | J14: https://minfi.gov.cm/wp-content/uploads/2025/01/Expose_Meesures_Fiscales_lancement_du_budget_2025_Fr.pdf
A15: conv_at | B15: Retenue sur assistance technique (convention FR-CM) | C15: 0.075 | D15: % | E15: 0.075 | F15: 0.075 | G15: Source | H15: milieu | I15: Assemblée nationale : rapport n° 35 (12e législature) sur l'avenant à la convention fiscale franco-camerounaise (confiance : high) | J15: https://www.assemblee-nationale.fr/12/pdf/rapports/r0035.pdf
A16: tsr | B16: TSR droit commun sur les autres prestations payées à l'étranger | C16: 0.15 | D16: % | E16: 0.15 | F16: 0.15 | G16: Source | H16: milieu | I16: MINFI : Régime fiscal des marchés publics (confiance : high) | J16: https://minfi.gov.cm/marches-publics/
A17: plafond_siege | B17: Plafond de déductibilité des frais de siège (% du bénéfice) | C17: 0.025 | D17: % | E17: 0.025 | F17: 0.025 | G17: Source | H17: milieu | I17: DGI Cameroun : Code Général des Impôts 2024 (version française) (confiance : high) | J17: https://www.impots.cm/sites/default/files/documents/CGI%202024%20version%20francaise.pdf
A18: dd_info | B18: Droit de douane, matériel informatique / photo (classement à confirmer) | C18: 0.1 | D18: % | E18: 0.1 | F18: 0.1 | G18: Source | H18: milieu | I18: LeFisk : Tarif douane Cameroun, taux par produit et guide CEMAC (confiance : low) | J18: https://lefisk.cm/blog/tarif-douane-cameroun-cemac-guide-complet
A19: dd_meubles | B19: Droit de douane, mobilier | C19: 0.2 | D19: % | E19: 0.2 | F19: 0.2 | G19: Source | H19: milieu | I19: Ecofin Agency : Cameroon adopts CEEAC-CEMAC common external tariff starting Jan. 1, 2026 (confiance : low) | J19: https://www.ecofinagency.com/news-services/1401-51923-cameroon-adopts-ceeac-cemac-common-external-tariff-starting-jan-1-2026
A20: tci | B20: Taxe communautaire d'intégration (TCI) | C20: 0.01 | D20: % | E20: 0.01 | F20: 0.01 | G20: Source | H20: milieu | I20: LeFisk : Simulateur frais de douane Cameroun 2026 (confiance : medium) | J20: https://lefisk.cm/outils/sim-douane
... A27: taxe_fonciere | B27: Taxe foncière annuelle (% de la valeur) | C27: 0.001 | D27: % | E27: 0.001 | F27: 0.001 | G27: Source | H27: milieu | I27: Camer.be : La connaissance de la taxe foncière au Cameroun (confiance : medium) | J27: https://www.camer.be/77824/33:30/cameroon-la-connaissance-de-la-taxe-fonciere-au-cameroun.html
A28: Émoluments du notaire (décret 95/038, par tranche)
A29: not_up1 | B29: Tranche 1 : borne haute | C29: 3000000 | D29: FCFA | G29: Hypothèse
A30: not_up2 | B30: Tranche 2 : borne haute | C30: 10000000 | D30: FCFA | G30: Hypothèse
A31: not_up3 | B31: Tranche 3 : borne haute | C31: 25000000 | D31: FCFA | G31: Hypothèse
A32: not_up4 | B32: Tranche 4 : borne haute | C32: 50000000 | D32: FCFA | G32: Hypothèse
A33: not_r1 | B33: Tranche 1 : taux | C33: 0.04 | D33: % | E33: 0.005 | F33: 0.04 | G33: Source | I33: Camer.be : La connaissance des émoluments et débours des notaires à l'occasion des ventes de terrains au Cameroun (confiance : medium) | J33: https://www.camer.be/67267/33:30/point-du-droit
A34: not_r2 | B34: Tranche 2 : taux | C34: 0.03 | D34: % | G34: Hypothèse
A35: not_r3 | B35: Tranche 3 : taux | C35: 0.015 | D35: % | G35: Hypothèse
A36: not_r4 | B36: Tranche 4 : taux | C36: 0.0075 | D36: % | G36: Hypothèse
A37: not_r5 | B37: Tranche 5 : taux | C37: 0.005 | D37: % | G37: Hypothèse
A38: Fiscalité France
A39: is_fr | B39: IS France, taux normal | C39: 0.25 | D39: % | E39: 0.25 | F39: 0.25 | G39: Source | I39: Loi de finances 2026 : 8 mesures à connaître (Extencia) (confiance : high) | J39: https://www.extencia.fr/loi-de-finances-2026-dirigeants
A40: qp_mf | B40: Quote-part imposable des dividendes (régime mère-fille) | C40: 0.05 | D40: % | E40: 0.05 | F40: 0.05 | G40: Source | I40: Conditions de l'exonération des dividendes versés aux sociétés mères (CMS Francis Lefebvre) (confiance : high) | J40: https://cms.law/en/fra/legal-updates/conditions-de-l-exoneration-des-dividendes-verses-aux-societes-meres
A41: fr_charges | B41: Charges patronales France (cadre, haut de fourchette, sans réduction RGDU) | C41: 0.45 | D41: % | E41: 0.42 | F41: 0.45 | G41: Source | H41: haut | I41: Coût salarial employeur et charges patronales 2026 (Simulateur Gratuit) (confiance : medium) | J41: https://simulateur-gratuit.fr/guide/cout-salarial-employeur-charges-patronales-2026/
A42: Social Cameroun
A43: pension_pf | B43: CNPS pension 4,2 % + prestations familiales 7 % (sous plafond) | C43: 0.112 | D43: % | E43: 0.112 | F43: 0.112 | G43: Source | I43: CNPS, décret 2016/072 (confiance : high) | J43: https://www.cleiss.fr/docs/cotisations/cameroun.html
A44: at_rate | B44: Accidents du travail, groupe B (1,75 à 5 %), non plafonné | C44: 0.025 | D44: % | G44: Hypothèse
A45: cnps_ceil | B45: Plafond mensuel CNPS | C45: 750000 | D45: FCFA | E45: 750000 | F45: 750000 | G45: Source | I45: CNPS, plafond de 750 000 FCFA (confiance : high) | J45: https://www.cleiss.fr/docs/cotisations/cameroun.html
A46: other_payroll | B46: Crédit foncier 1,5 % + FNE 1 % (sur tout le brut) | C46: 0.025 | D46: % | E46: 0.025 | F46: 0.025 | G46: Source | I46: MINFI / PwC : CFC patronal 1,5 %, FNE 1 % (confiance : high) | J46: https://minfi.gov.cm/les-autres-retenues-sur-les-salaires/
A47: treizieme | B47: Mois payés par an (13e mois, convention du commerce) | C47: 13 | D47: mois | E47: 13 | F47: 13 | G47: Source | I47: Convention Collective Nationale du Commerce (texte PDF) (confiance : low) | J47: https://www.fotouni.net/codefo/pdf/Conv-Collective-Nat-du-Commerce.pdf
A48: transport_day | B48: Indemnité de transport par jour travaillé | C48: 1300 | D48: FCFA/jour | E48: 1300 | F48: 1300 | G48: Source | I48: CAMEROUN : La convention collective nationale du commerce révisée – Droit Médias Finance (confiance : medium) | J48: https://droitmediasfinance.com/index.php/actualites/droit-ohada-affaires/701-cameroun-la-convention-collective-nationale-du-commerce-revisee
A49: days_office | B49: Jours travaillés, équipes de bureau | C49: 22 | D49: jours | G49: Hypothèse
A50: days_field | B50: Jours travaillés, hub et livraison | C50: 26 | D50: jours | G50: Hypothèse
A51: garde_price | B51: Gardiennage : prix facturé par agent et par mois | C51: 142500 | D51: FCFA/mois | E51: 135000 | F51: 150000 | G51: Source | H51: milieu | I51: Gardiennage – Mercuriale de prix 2020 – Magazine Comptable-Matières (lacooperative.cm) (confiance : low) | J51: http://www.lacooperative.cm/pages/outils-de-gestion/mercuriale-de-prix-2020/gardiennage.html
A52: garde_fte | B52: Équivalents temps plein pour un poste 24h/24 | C52: 4.2 | D52: ETP | G52: Hypothèse
A53: Salaires bruts mensuels Cameroun
A54: sal_dg | B54: Salaire brut : dg | C54: 1000000 | D54: FCFA/mois | E54: 1000000 | F54: 5000000 | G54: Source | H54: bas | I54: Salaire Moyen Cameroun 2026 : par secteur, métier et expérience – Infospratiques (confiance : low) | J54: https://infospratiques.cm/salaire-moyen-cameroun/
A55: sal_hub_manager | B55: Salaire brut : hub_manager | C55: 575000 | D55: FCFA/mois | E55: 350000 | F55: 800000 | G55: Source | H55: milieu | I55: Formation Supply Chain et Logistique internationale au Cameroun : salaires, débouchés – PIDERC (confiance : low) | J55: https://piderc.org/formation-supply-chain-cameroun-salaires-debouches-et-classement-2025/
A56: sal_agent_hub | B56: Salaire brut : agent_hub | C56: 100000 | D56: FCFA/mois | E56: 80000 | F56: 120000 | G56: Source | H56: milieu | I56: Salaires à Douala en 2026 : grille complète par secteur et métier – OpenShores (confiance : medium) | J56: https://www.openshores.co/blog/cameroun/douala/salaires-a-douala
A57: sal_magasinier | B57: Salaire brut : magasinier | C57: 167500 | D57: FCFA/mois | E57: 85000 | F57: 250000 | G57: Source | H57: milieu | I57: Salaires moyens au Cameroun – Douane, transit, logistique, transport – PIDERC (confiance : low) | J57: https://piderc.org/salaires-moyens-au-cameroun-douane-transit-declarant-en-douane-logistique-transport/
A58: sal_livreur | B58: Salaire brut : livreur | C58: 80000 | D58: FCFA/mois | E58: 60000 | F58: 100000 | G58: Source | H58: milieu | I58: Salaires moyens au Cameroun par secteur en 2026 – Job Cameroun (confiance : medium) | J58: https://job-cameroun.com/blog/salaires-moyens-cameroun-2026
A59: sal_chauffeur | B59: Salaire brut : chauffeur | C59: 105000 | D59: FCFA/mois | E59: 60000 | F59: 150000 | G59: Source | H59: milieu | I59: Salaires moyens au Cameroun par secteur en 2026 – Job Cameroun (confiance : medium) | J59: https://job-cameroun.com/blog/salaires-moyens-cameroun-2026
A60: sal_receptionniste | B60: Salaire brut : receptionniste | C60: 95000 | D60: FCFA/mois | E60: 70000 | F60: 120000 | G60: Source | H60: milieu | I60: Bilingual Receptionist (Réceptionniste bilingue) – Yaoundé – 80 000 F CFA par mois – EmploisCameroun (confiance : medium) | J60: https://emploiscameroun.com/offre/50356-bilingual-receptionist-receptionniste-bilingue-yaounde-80-000-f-cfa-par-mois/
A61: sal_cm | B61: Salaire brut : cm | C61: 200000 | D61: FCFA/mois | E61: 150000 | F61: 250000 | G61: Source | H61: milieu | I61: Community manager au Cameroun : compétences, formation, IA – Econuma (confiance : medium) | J61: https://econuma.com/go-digital/community-manager-cameroun-competences-formation-ia-1778596620
A62: sal_photographe | B62: Salaire brut : photographe (proxy : graphiste) | C62: 237500 | D62: FCFA/mois | E62: 100000 | F62: 375000 | G62: Source | H62: milieu | I62: Salaire : Graphiste (mai 2026) – Cameroun – Glassdoor (confiance : low) | J62: https://www.glassdoor.fr/Salaires/cameroon-graphiste-salaire-SRCH_IL.0,8_IN52_KO9,18.htm
A63: sal_videaste | B63: Salaire brut : videaste | C63: 105000 | D63: FCFA/mois | E63: 60000 | F63: 150000 | G63: Source | H63: milieu | I63: Reconversion professionnelle : 15 métiers porteurs sans diplôme en 2026 – CameroonDesks (confiance : low) | J63: https://www.cameroondesks.com/2025/12/reconversion-professionnelle-15-metiers-sans-diplome-sty.html
A64: sal_graphiste | B64: Salaire brut : graphiste | C64: 237500 | D64: FCFA/mois | E64: 100000 | F64: 375000 | G64: Source | H64: milieu | I64: Salaire : Graphiste (mai 2026) – Cameroun – Glassdoor (confiance : low) | J64: https://www.glassdoor.fr/Salaires/cameroon-graphiste-salaire-SRCH_IL.0,8_IN52_KO9,18.htm
A65: sal_dev | B65: Salaire brut : dev | C65: 475000 | D65: FCFA/mois | E65: 150000 | F65: 800000 | G65: Source | H65: milieu | I65: Salaires au Cameroun en 2026 : la grille de référence par métier – Pem's Recruitment (confiance : medium) | J65: https://pems-recruitment.com/blog/salaires-cameroun-2026-grille-reference
... A71: sal_sav | B71: Salaire brut : sav (proxy : réceptionniste) | C71: 95000 | D71: FCFA/mois | E71: 70000 | F71: 120000 | G71: Source | H71: milieu | I71: Bilingual Receptionist (Réceptionniste bilingue) – Yaoundé – 80 000 F CFA par mois – EmploisCameroun (confiance : medium) | J71: https://emploiscameroun.com/offre/50356-bilingual-receptionist-receptionniste-bilingue-yaounde-80-000-f-cfa-par-mois/
A72: Siège France
A73: smic | B73: SMIC brut mensuel (juin 2026) | C73: 1867.02 | D73: €/mois | E73: 1867.02 | F73: 1867.02 | G73: Source | I73: Le SMIC revalorisé le 1er juin 2026 (info.gouv.fr) ; Revalorisation du Smic au 1er juin 2026 (Centre Inffo) (confiance : high) | J73: https://www.info.gouv.fr/public/index.php/actualite/le-smic-revalorise-le-1er-juin-2026
A74: fr_sal_cdg | B74: Contrôleur de gestion / finance groupe (brut annuel) | C74: 49500 | D74: €/an | E74: 43000 | F74: 56000 | G74: Source | H74: milieu | I74: Salaire > Contrôleur de gestion (blog-rh.com, citant Apec, Jobted, Le Figaro Emploi) (confiance : medium) | J74: https://www.blog-rh.com/salaire-controleur-de-gestion/
A75: fr_sal_achats | B75: Coordinateur achats & import (brut annuel) | C75: 40000 | D75: €/an | E75: 35000 | F75: 45000 | G75: Source | H75: milieu | I75: Gestionnaire import export – salaire (Robert Half France) (confiance : medium) | J75: https://www.roberthalf.com/fr/fr/details-emploi/gestionnaire-import-export
A76: fr_loyer | B76: Loyer de bureaux (ex. Lyon), €/m²/an HT HC | C76: 215.5 | D76: €/m²/an | E76: 198 | F76: 233 | G76: Source | H76: milieu | I76: Analyses du marché tertiaire lyonnais au S1 2025 (JLL / CECIM) (confiance : high) | J76: https://www.jll.com/fr-fr/newsroom/lyon-chiffres-cecim-s1-2025
A77: fr_m2 | B77: Surface du siège France | C77: 60 | D77: m² | G77: Hypothèse
A78: fr_compta | B78: Expert-comptable (annuel) | C78: 5000 | D78: €/an | E78: 2000 | F78: 8000 | G78: Source | H78: milieu | I78: Quel est le prix d'un expert-comptable ? (Keobiz) ; Grille tarifaire expert-comptable 2026 (Hayot Expertise) (confiance : medium) | J78: https://www.keobiz.fr/fiches-pratiques/creation-dentreprise/quel-est-le-prix-dun-expert-comptable/
A79: fr_rcpro | B79: Assurance RC Pro (annuelle) | C79: 3100 | D79: €/an | E79: 200 | F79: 6000 | G79: Source | H79: milieu | I79: RC pro informatique : tarifs et garanties (Philtr) (confiance : medium) | J79: https://philtr.fr/responsabilite-civile-professionnelle/metier/informatique
A80: fr_banque | B80: Compte bancaire professionnel (mensuel) | C80: 29.5 | D80: €/mois | E80: 9 | F80: 50 | G80: Source | H80: milieu | I80: Qonto vs Shine vs banque traditionnelle : quel compte pro choisir en 2026 ? (Hayot Expertise) (confiance : medium) | J80: https://hayot-expertise.fr/blog/qonto-vs-shine-vs-banque-traditionnelle-compte-pro
A81: Immobilier et construction
A82: c_std | B82: Construction, finition standard | C82: 150000 | D82: FCFA/m² | E82: 120000 | F82: 180000 | G82: Source | H82: milieu | I82: Infospratiques.cm : Coût de construction d'une maison au Cameroun (confiance : medium) | J82: https://infospratiques.cm/cout-construction-maison-cameroun/
A83: c_haut | B83: Construction, haut standing (matériaux importés) | C83: 365000 | D83: FCFA/m² | E83: 280000 | F83: 450000 | G83: Source | H83: milieu | I83: Infospratiques.cm : Coût de construction d'une maison au Cameroun (confiance : medium) | J83: https://infospratiques.cm/cout-construction-maison-cameroun/
A84: circ | B84: Circulations et locaux techniques | C84: 0.15 | D84: % | G84: Hypothèse
A85: land_yde | B85: Terrain, quartiers intermédiaires (Mvan, Nkolbisson) | C85: 37500 | D85: FCFA/m² | E85: 25000 | F85: 50000 | G85: Source | H85: milieu | I85: Infospratiques.cm : Prix du terrain au Cameroun, Douala, Yaoundé et régions (confiance : medium) | J85: https://infospratiques.cm/?p=157
A86: land_m2_yde | B86: Surface du terrain, maison mère Yaoundé | C86: 2500 | D86: m² | G86: Hypothèse
A87: cloture_ttc | B87: Mur de clôture : plafond de marché public TTC | C87: 210526 | D87: FCFA/ml | E87: 210526 | F87: 210526 | G87: Source | I87: ARMP : Avis d'appel d'offres 004 AONO, commune de Gazawa (construction d'un mur de clôture) (confiance : low) | J87: https://pridesoft.armp.cm/_lib/file/doc/0903/2024/01/31/C_GAZAWA/004%20AONO%20GAZ(1).pdf
A88: land_dla | B88: Terrain, Bonabéri (Douala), aussi retenu pour les villes moyennes | C88: 60000 | D88: FCFA/m² | E88: 40000 | F88: 80000 | G88: Source | H88: milieu | I88: Expat.com : Terrain 1000 m² à vendre à Bonaberi Douala (confiance : medium) | J88: https://www.expat.com/fr/immobilier/afrique/cameroun/douala/44-terrains-a-vendre/775340-terrain-1000m2-a-vendre-a-bonaberi-douala.html
A89: Import, flotte, énergie
A90: freight_eur | B90: Fret Le Havre → Kribi, conteneur 40' (2022, à actualiser) | C90: 2875 | D90: € | E90: 2875 | F90: 2875 | G90: Source | I90: AJOT — CMA CGM FAK rates from North Europe to West Africa (confiance : low) | J90: https://www.ajot.com/news/cma-cgm-fak-rates-from-north-europe-west-mediterranean-atlantic-adriatic-baltic-scandinavia-to-west-africa
A91: pss_eur | B91: Surcharge haute saison par EVP (40' = 2 EVP) | C91: 85 | D91: €/EVP | E91: 85 | F91: 85 | G91: Source | I91: Container News — CMA CGM announces PSS on Douala (confiance : medium) | J91: https://container-news.com/cma-cgm-announces-pss-on-douala-shipments/
A92: transit | B92: Commissionnaire en douane, frais de dossier | C92: 25000 | D92: FCFA | E92: 25000 | F92: 25000 | G92: Source | I92: Memoireonline – La facturation chez les commissionnaires en douane agréés (cas EOLIS Cameroun) (confiance : low) | J92: https://www.memoireonline.com/04/12/5722/m_La-facturation-chez-les-commissionnaires-en-douane-agreescas-dEOLIS-Cameroun4.html
A93: moto | B93: Moto de livraison 125-150 cm³ avec papiers | C93: 544500 | D93: FCFA | E93: 450000 | F93: 639000 | G93: Source | H93: milieu | I93: CoinAfrique (Nanfan 150, 2024 : 450 000-550 000) et financement Advans/Bee (≈ 639 000 avec papiers) (confiance : low) | J93: https://cm.coinafrique.com/categorie/motos-et-scooters/nanfan
A94: van | B94: Utilitaire Toyota Hiace d'occasion (annonce Douala) | C94: 12500000 | D94: FCFA | E94: 12500000 | F94: 12500000 | G94: Source | I94: Voitures Toyota hiace zoom 2011 neufs et occasions au Cameroun – CoinAfrique Cameroun – 5057538 (confiance : low) | J94: https://cm.coinafrique.com/annonce/voitures/toyota-hiace-zoom-2011-5057538
A95: car | B95: Véhicule de service Toyota Hilux 2020 | C95: 16681700 | D95: FCFA | E95: 12789300 | F95: 20574100 | G95: Source | H95: milieu | I95: Afrotools — 2020 Toyota Hilux, Cameroon planning snapshot (confiance : medium) | J95: https://afrotools.com/cars/cameroon/toyota/hilux/2020/
A96: n_moto | B96: Nombre de motos | C96: 8 | D96: unités | G96: Hypothèse
A97: n_van | B97: Nombre d'utilitaires | C97: 1 | D97: unités | G97: Hypothèse
A98: n_car | B98: Nombre de véhicules de service | C98: 1 | D98: unités | G98: Hypothèse
A99: fuel | B99: Super, prix pompe | C99: 840 | D99: FCFA/L | E99: 840 | F99: 840 | G99: Source | I99: Prix du Carburant au Cameroun 2026 : Tarifs (infospratiques.cm) (confiance : high) | J99: https://infospratiques.cm/prix-carburant-cameroun/
A100: gasoil | B100: Gasoil, prix pompe | C100: 828 | D100: FCFA/L | E100: 828 | F100: 828 | G100: Source | I100: Prix du Carburant au Cameroun 2026 : Tarifs (infospratiques.cm) (confiance : high) | J100: https://infospratiques.cm/prix-carburant-cameroun/
A101: conso_moto | B101: Consommation réelle moto 125 cm³ (haut, usage urbain chargé) | C101: 2.72 | D101: L/100 km | E101: 1.85 | F101: 2.72 | G101: Source | H101: haut | I101: Spritmonitor – Honda CB 125 F (relevés utilisateur) (confiance : medium) | J101: https://www.spritmonitor.de/fr/detail/1343341.html?cdetail=1
A102: deliv_day | B102: Livraisons par coursier et par jour (bas de 12-15) | C102: 12 | D102: livraisons | E102: 12 | F102: 15 | G102: Source | H102: bas | I102: Cameroon Tribune : coursier à la course, 12 à 15 livraisons/jour (confiance : low) | J102: https://cameroon-tribune.cm/article.html/79064/fr.html/livraison-colis-les-motos-taxis-facilitent-la-tache
A103: km_deliv | B103: Kilomètres par livraison (aller-retour moyen) | C103: 10 | D103: km | G103: Hypothèse
A104: van_km | B104: Kilométrage mensuel de l'utilitaire | C104: 2000 | D104: km | G104: Hypothèse
A105: van_conso | B105: Consommation de l'utilitaire | C105: 10 | D105: L/100 km | G105: Hypothèse
A106: eneo | B106: Électricité ENEO BT non résidentielle (tranche haute) | C106: 99 | D106: FCFA/kWh | E106: 84 | F106: 99 | G106: Source | H106: haut | I106: Cameroon ENEO Tariffs website (ESMAP RISE, capture de la page tarifs ENEO) (confiance : medium) | J106: https://rise.esmap.org/data/files/library/cameroon/Electricity Access/Cameroon_ENEO Tariffs website.pdf
A107: kwh | B107: Consommation électrique mensuelle de la maison mère | C107: 6000 | D107: kWh | G107: Hypothèse
A108: internet | B108: Accès internet professionnel | C108: 32500 | D108: FCFA/mois | E108: 20000 | F108: 45000 | G108: Source | H108: milieu | I108: Ecomatin : TIC, le Cameroun compte plus de 50 fournisseurs d'accès Internet en activité (confiance : low) | J108: https://ecomatin.net/tic-le-cameroun-compte-plus-de-50-fournisseurs-dacces-internet-en-activite
A109: n_lines | B109: Lignes internet (redondance) | C109: 2 | D109: lignes | G109: Hypothèse
A110: adobe | B110: Adobe Creative Cloud Pro, par utilisateur | C110: 80.07 | D110: €/mois | E110: 78.65 | F110: 81.49 | G110: Source | H110: milieu | I110: FranceFG – Adobe Creative Cloud prix 2026 comparatif (confiance : low) | J110: https://francefg.fr/photoshop/adobe-creative-cloud-prix-2026-comparatif/
A111: adobe_users | B111: Utilisateurs Adobe | C111: 3 | D111: licences | G111: Hypothèse
A112: Durées d'amortissement (hypothèses à valider ; plafonds : CGI art. 7)
...

Sheet Masse salariale
A1: Masse salariale mensuelle — maison mère de Yaoundé et siège France
A3: Poste | B3: Pôle | C3: Effectif | D3: Brut mensuel | E3: Charges patronales | F3: Jours (transport) | G3: Coût chargé / mois | H3: Total mensuel
A4: Directeur général Afrique | B4: Direction | C4: 1 | D4: =Hypothèses!$C$54 -> 1000000 | E4: =MIN(D4,Hypothèses!$C$45)*Hypothèses!$C$43+D4*(Hypothèses!$C$44+Hypothèses!$C$46) -> 134000 | F4: =Hypothèses!$C$49 -> 22 | G4: =(D4+E4)*Hypothèses!$C$47/12+Hypothèses!$C$48*F4 -> 1257100 | H4: =C4*G4 -> 1257100
A5: Responsable hub & logistique | B5: Opérations | C5: 1 | D5: =Hypothèses!$C$55 -> 575000 | E5: =MIN(D5,Hypothèses!$C$45)*Hypothèses!$C$43+D5*(Hypothèses!$C$44+Hypothèses!$C$46) -> 93150 | F5: =Hypothèses!$C$50 -> 26 | G5: =(D5+E5)*Hypothèses!$C$47/12+Hypothèses!$C$48*F5 -> 757629.17 | H5: =C5*G5 -> 757629.17
A6: Agents de hub (réception, scan, stock) | B6: Opérations | C6: 4 | D6: =Hypothèses!$C$56 -> 100000 | E6: =MIN(D6,Hypothèses!$C$45)*Hypothèses!$C$43+D6*(Hypothèses!$C$44+Hypothèses!$C$46) -> 16200 | F6: =Hypothèses!$C$50 -> 26 | G6: =(D6+E6)*Hypothèses!$C$47/12+Hypothèses!$C$48*F6 -> 159683.33 | H6: =C6*G6 -> 638733.33
A7: Magasinier | B7: Opérations | C7: 1 | D7: =Hypothèses!$C$57 -> 167500 | E7: =MIN(D7,Hypothèses!$C$45)*Hypothèses!$C$43+D7*(Hypothèses!$C$44+Hypothèses!$C$46) -> 27135 | F7: =Hypothèses!$C$50 -> 26 | G7: =(D7+E7)*Hypothèses!$C$47/12+Hypothèses!$C$48*F7 -> 244654.58 | H7: =C7*G7 -> 244654.58
A8: Livreurs moto salariés | B8: Opérations | C8: 8 | D8: =Hypothèses!$C$58 -> 80000 | E8: =MIN(D8,Hypothèses!$C$45)*Hypothèses!$C$43+D8*(Hypothèses!$C$44+Hypothèses!$C$46) -> 12960 | F8: =Hypothèses!$C$50 -> 26 | G8: =(D8+E8)*Hypothèses!$C$47/12+Hypothèses!$C$48*F8 -> 134506.67 | H8: =C8*G8 -> 1076053.3
A9: Chauffeur utilitaire | B9: Opérations | C9: 1 | D9: =Hypothèses!$C$59 -> 105000 | E9: =MIN(D9,Hypothèses!$C$45)*Hypothèses!$C$43+D9*(Hypothèses!$C$44+Hypothèses!$C$46) -> 17010 | F9: =Hypothèses!$C$50 -> 26 | G9: =(D9+E9)*Hypothèses!$C$47/12+Hypothèses!$C$48*F9 -> 165977.5 | H9: =C9*G9 -> 165977.5
A10: Réceptionniste | B10: Clients & vendeurs | C10: 1 | D10: =Hypothèses!$C$60 -> 95000 | E10: =MIN(D10,Hypothèses!$C$45)*Hypothèses!$C$43+D10*(Hypothèses!$C$44+Hypothèses!$C$46) -> 15390 | F10: =Hypothèses!$C$49 -> 22 | G10: =(D10+E10)*Hypothèses!$C$47/12+Hypothèses!$C$48*F10 -> 148189.17 | H10: =C10*G10 -> 148189.17
A11: Agents SAV / litiges | B11: Clients & vendeurs | C11: 2 | D11: =Hypothèses!$C$71 -> 95000 | E11: =MIN(D11,Hypothèses!$C$45)*Hypothèses!$C$43+D11*(Hypothèses!$C$44+Hypothèses!$C$46) -> 15390 | F11: =Hypothèses!$C$49 -> 22 | G11: =(D11+E11)*Hypothèses!$C$47/12+Hypothèses!$C$48*F11 -> 148189.17 | H11: =C11*G11 -> 296378.33
A12: Commerciaux vendeurs (growth) | B12: Clients & vendeurs | C12: 2 | D12: =Hypothèses!$C$70 -> 190000 | E12: =MIN(D12,Hypothèses!$C$45)*Hypothèses!$C$43+D12*(Hypothèses!$C$44+Hypothèses!$C$46) -> 30780 | F12: =Hypothèses!$C$49 -> 22 | G12: =(D12+E12)*Hypothèses!$C$47/12+Hypothèses!$C$48*F12 -> 267778.33 | H12: =C12*G12 -> 535556.67
A13: Photographe produit (lead studio) | B13: Studio Premium | C13: 1 | D13: =Hypothèses!$C$62 -> 237500 | E13: =MIN(D13,Hypothèses!$C$45)*Hypothèses!$C$43+D13*(Hypothèses!$C$44+Hypothèses!$C$46) -> 38475 | F13: =Hypothèses!$C$49 -> 22 | G13: =(D13+E13)*Hypothèses!$C$47/12+Hypothèses!$C$48*F13 -> 327572.92 | H13: =C13*G13 -> 327572.92
A14: Vidéaste / monteur | B14: Studio Premium | C14: 1 | D14: =Hypothèses!$C$63 -> 105000 | E14: =MIN(D14,Hypothèses!$C$45)*Hypothèses!$C$43+D14*(Hypothèses!$C$44+Hypothèses!$C$46) -> 17010 | F14: =Hypothèses!$C$49 -> 22 | G14: =(D14+E14)*Hypothèses!$C$47/12+Hypothèses!$C$48*F14 -> 160777.5 | H14: =C14*G14 -> 160777.5
A15: Graphiste-retoucheur & impression | B15: Studio Premium | C15: 1 | D15: =Hypothèses!$C$64 -> 237500 | E15: =MIN(D15,Hypothèses!$C$45)*Hypothèses!$C$43+D15*(Hypothèses!$C$44+Hypothèses!$C$46) -> 38475 | F15: =Hypothèses!$C$49 -> 22 | G15: =(D15+E15)*Hypothèses!$C$47/12+Hypothèses!$C$48*F15 -> 327572.92 | H15: =C15*G15 -> 327572.92
A16: Développeurs full-stack | B16: Informatique & tracking | C16: 2 | D16: =Hypothèses!$C$65 -> 475000 | E16: =MIN(D16,Hypothèses!$C$45)*Hypothèses!$C$43+D16*(Hypothèses!$C$44+Hypothèses!$C$46) -> 76950 | F16: =Hypothèses!$C$49 -> 22 | G16: =(D16+E16)*Hypothèses!$C$47/12+Hypothèses!$C$48*F16 -> 626545.83 | H16: =C16*G16 -> 1253091.7
A17: Analyste data (salle de tracking) | B17: Informatique & tracking | C17: 1 | D17: =Hypothèses!$C$66 -> 475000 | E17: =MIN(D17,Hypothèses!$C$45)*Hypothèses!$C$43+D17*(Hypothèses!$C$44+Hypothèses!$C$46) -> 76950 | F17: =Hypothèses!$C$49 -> 22 | G17: =(D17+E17)*Hypothèses!$C$47/12+Hypothèses!$C$48*F17 -> 626545.83 | H17: =C17*G17 -> 626545.83
A18: Community manager (tracking réseaux) | B18: Informatique & tracking | C18: 1 | D18: =Hypothèses!$C$61 -> 200000 | E18: =MIN(D18,Hypothèses!$C$45)*Hypothèses!$C$43+D18*(Hypothèses!$C$44+Hypothèses!$C$46) -> 32400 | F18: =Hypothèses!$C$49 -> 22 | G18: =(D18+E18)*Hypothèses!$C$47/12+Hypothèses!$C$48*F18 -> 280366.67 | H18: =C18*G18 -> 280366.67
A19: Comptable | B19: Support | C19: 1 | D19: =Hypothèses!$C$67 -> 325000 | E19: =MIN(D19,Hypothèses!$C$45)*Hypothèses!$C$43+D19*(Hypothèses!$C$44+Hypothèses!$C$46) -> 52650 | F19: =Hypothèses!$C$49 -> 22 | G19: =(D19+E19)*Hypothèses!$C$47/12+Hypothèses!$C$48*F19 -> 437720.83 | H19: =C19*G19 -> 437720.83
A20: RH & formation (Academy) | B20: Support | C20: 1 | D20: =Hypothèses!$C$68 -> 205000 | E20: =MIN(D20,Hypothèses!$C$45)*Hypothèses!$C$43+D20*(Hypothèses!$C$44+Hypothèses!$C$46) -> 33210 | F20: =Hypothèses!$C$49 -> 22 | G20: =(D20+E20)*Hypothèses!$C$47/12+Hypothèses!$C$48*F20 -> 286660.83 | H20: =C20*G20 -> 286660.83
A21: Agent d'entretien | B21: Support | C21: 1 | D21: =Hypothèses!$C$69 -> 60000 | E21: =MIN(D21,Hypothèses!$C$45)*Hypothèses!$C$43+D21*(Hypothèses!$C$44+Hypothèses!$C$46) -> 9720 | F21: =Hypothèses!$C$49 -> 22 | G21: =(D21+E21)*Hypothèses!$C$47/12+Hypothèses!$C$48*F21 -> 104130 | H21: =C21*G21 -> 104130
A22: Total salariés Yaoundé | C22: =SUM(C4:C21) -> 31 | H22: =SUM(H4:H21) -> 8924711.2
A23: Gardiennage (1 poste 24h/24, société agréée) | C23: =Hypothèses!$C$52 -> 4.2 | G23: =Hypothèses!$C$51 -> 142500 | H23: =C23*G23 -> 598500
A25: Siège France | C25: Effectif | D25: Brut annuel (€) | E25: Charges (€) | G25: Coût annuel (€) | H25: Coût mensuel (FCFA)
A26: Président-fondateur (rémunéré au SMIC au démarrage) | C26: 1 | D26: =Hypothèses!$C$73*12 -> 22404.24 | E26: =D26*Hypothèses!$C$41 -> 10081.908 | G26: =C26*(D26+E26) -> 32486.148 | H26: =G26/12*Hypothèses!$C$6 -> 1775793
A27: Contrôleur de gestion / finance groupe | C27: 1 | D27: =Hypothèses!$C$74 -> 49500 | E27: =D27*Hypothèses!$C$41 -> 22275 | G27: =C27*(D27+E27) -> 71775 | H27: =G27/12*Hypothèses!$C$6 -> 3923442.8
A28: Coordinateur achats & import (sourcing Europe) | C28: 1 | D28: =Hypothèses!$C$75 -> 40000 | E28: =D28*Hypothèses!$C$41 -> 18000 | G28: =C28*(D28+E28) -> 58000 | H28: =G28/12*Hypothèses!$C$6 -> 3170458.8
A29: Total siège France | G29: =SUM(G26:G28) -> 162261.15

Sheet Maison mère Yaoundé
A1: Maison mère Afrique (Yaoundé) — programme des espaces et investissement immobilier
A3: Espace | B3: Surface (m²) | C3: Standing | D3: Coût / m² (FCFA) | E3: Coût de construction (FCFA) | F3: Part du coût du bâtiment
A4: Réception & contrôle des produits (quai) | B4: 120 | C4: entrepot | D4: =IF(C4="haut",Hypothèses!$C$83,Hypothèses!$C$82) -> 150000 | E4: =B4*D4 -> 18000000 | F4: =E4/SUM($E$4:$E$14) -> 0.074673304
A5: Stockage (hub Yaoundé) | B5: 400 | C5: entrepot | D5: =IF(C5="haut",Hypothèses!$C$83,Hypothèses!$C$82) -> 150000 | E5: =B5*D5 -> 60000000 | F5: =E5/SUM($E$4:$E$14) -> 0.24891101
A6: Studio Premium haut standing (plateau, loge, post-prod) | B6: 150 | C6: haut | D6: =IF(C6="haut",Hypothèses!$C$83,Hypothèses!$C$82) -> 365000 | E6: =B6*D6 -> 54750000 | F6: =E6/SUM($E$4:$E$14) -> 0.2271313
A7: Pôle informatique | B7: 60 | C7: standard | D7: =IF(C7="haut",Hypothèses!$C$83,Hypothèses!$C$82) -> 150000 | E7: =B7*D7 -> 9000000 | F7: =E7/SUM($E$4:$E$14) -> 0.037336652
A8: Salle de tracking des produits gagnants | B8: 40 | C8: standard | D8: =IF(C8="haut",Hypothèses!$C$83,Hypothèses!$C$82) -> 150000 | E8: =B8*D8 -> 6000000 | F8: =E8/SUM($E$4:$E$14) -> 0.024891101
A9: Bureaux des équipes (ops, SAV, vendeurs, finance, RH) | B9: 160 | C9: standard | D9: =IF(C9="haut",Hypothèses!$C$83,Hypothèses!$C$82) -> 150000 | E9: =B9*D9 -> 24000000 | F9: =E9/SUM($E$4:$E$14) -> 0.099564406
A10: Salle de formation (Academy, 20 places) | B10: 70 | C10: standard | D10: =IF(C10="haut",Hypothèses!$C$83,Hypothèses!$C$82) -> 150000 | E10: =B10*D10 -> 10500000 | F10: =E10/SUM($E$4:$E$14) -> 0.043559428
A11: Atelier d'impression des affiches | B11: 40 | C11: standard | D11: =IF(C11="haut",Hypothèses!$C$83,Hypothèses!$C$82) -> 150000 | E11: =B11*D11 -> 6000000 | F11: =E11/SUM($E$4:$E$14) -> 0.024891101
A12: Salles de réunion (x2) | B12: 50 | C12: haut | D12: =IF(C12="haut",Hypothèses!$C$83,Hypothèses!$C$82) -> 365000 | E12: =B12*D12 -> 18250000 | F12: =E12/SUM($E$4:$E$14) -> 0.075710434
A13: Bureaux des membres clés (x4) | B13: 70 | C13: haut | D13: =IF(C13="haut",Hypothèses!$C$83,Hypothèses!$C$82) -> 365000 | E13: =B13*D13 -> 25550000 | F13: =E13/SUM($E$4:$E$14) -> 0.10599461
A14: Sanitaires, vestiaires, espace pause | B14: 60 | C14: standard | D14: =IF(C14="haut",Hypothèses!$C$83,Hypothèses!$C$82) -> 150000 | E14: =B14*D14 -> 9000000 | F14: =E14/SUM($E$4:$E$14) -> 0.037336652
A15: Circulations et locaux techniques (réparties au prorata) | B15: =ROUND(SUM(B4:B14)*Hypothèses!$C$84,0) -> 183 | C15: standard | D15: =Hypothèses!$C$82 -> 150000 | E15: =B15*D15 -> 27450000
A16: Surface de plancher et coût de construction | B16: =SUM(B4:B15) -> 1403 | E16: =SUM(E4:E15) -> 268500000
A18: Terrain (prix × surface) | E18: =Hypothèses!$C$85*Hypothèses!$C$86 -> 93750000
A19: Droits d'enregistrement 5 % + conservation foncière 2 % | E19: =E18*(Hypothèses!$C$24+Hypothèses!$C$25) -> 6562500
A20: Émoluments du notaire (barème par tranche) | E20: =MIN(E18,Hypothèses!$C$29)*Hypothèses!$C$33+MAX(0,MIN(E18,Hypothèses!$C$30)-Hypothèses!$C$29)*Hypothèses!$C$34+MAX(0,MIN(E18,Hypothèses!$C$31)-Hypothèses!$C$30)*Hypothèses!$C$35+MAX(0,MIN(E18,Hypothèses!$C$32)-Hypothèses!$C$31)*Hypothèses!$C$36+MAX(0,E18-Hypothèses!$C$32)*Hypothèses!$C$37 -> 961250
A21: Permis de bâtir | E21: =E16*Hypothèses!$C$26 -> 2685000
A22: Mur de clôture HT (périmètre d'un terrain carré × prix HT) | E22: =4*SQRT(Hypothèses!$C$86)*Hypothèses!$C$87/(1+Hypothèses!$C$12) -> 35308344
A23: Construction | E23: =E16 -> 268500000
A24: INVESTISSEMENT IMMOBILIER (hors parking pavé, VRD, forage : sur devis) | E24: =SUM(E18:E23) -> 4.0776709e+08

Sheet Équipements importés
A1: Équipements achetés en France (HT export), fret, douane camerounaise → coût rendu
A3: Désignation | B3: Groupe | C3: Qté | D3: Prix unitaire (€) | E3: Base | F3: Prix HT export (€) | G3: Valeur FOB (FCFA) | H3: Quote-part fret (FCFA) | I3: Valeur CAF (FCFA) | J3: Droit de douane | K3: Autres prélèvements | L3: Droits et taxes (FCFA) | M3: Coût rendu (FCFA) | N3: Source
A4: Boîtier Sony A7 IV | B4: Studio | C4: 2 | D4: 2124 | E4: TTC | F4: =IF(E4="TTC",D4/(1+Hypothèses!$C$7),D4) -> 1770 | G4: =C4*F4*Hypothèses!$C$6 -> 2322087.8 | H4: =G4/SUM($G$4:$G$22)*(Hypothèses!$C$90+2*Hypothèses!$C$91)*Hypothèses!$C$6 -> 68924.217 | I4: =G4+H4 -> 2391012 | J4: =Hypothèses!$C$18 -> 0.1 | K4: =Hypothèses!$C$20+Hypothèses!$C$21+Hypothèses!$C$22+Hypothèses!$C$23 -> 0.0245 | L4: =I4*(J4+K4) -> 297680.99 | M4: =I4+L4 -> 2688693 | N4: https://www.boulanger.com/ref/1172131
A5: Objectif Sony FE 90 mm Macro G | B5: Studio | C5: 1 | D5: 929 | E5: TTC | F5: =IF(E5="TTC",D5/(1+Hypothèses!$C$7),D5) -> 774.16667 | G5: =C5*F5*Hypothèses!$C$6 -> 507820.04 | H5: =G5/SUM($G$4:$G$22)*(Hypothèses!$C$90+2*Hypothèses!$C$91)*Hypothèses!$C$6 -> 15073.116 | I5: =G5+H5 -> 522893.16 | J5: =Hypothèses!$C$18 -> 0.1 | K5: =Hypothèses!$C$20+Hypothèses!$C$21+Hypothèses!$C$22+Hypothèses!$C$23 -> 0.0245 | L5: =I5*(J5+K5) -> 65100.198 | M5: =I5+L5 -> 587993.36 | N5: https://www.qualescegliere.it/gtin_obiettivi-per-fotocamere/4548736007970/
A6: Objectif Sony FE 24-70 mm f/2.8 GM II | B6: Studio | C6: 1 | D6: 1961 | E6: TTC | F6: =IF(E6="TTC",D6/(1+Hypothèses!$C$7),D6) -> 1634.1667 | G6: =C6*F6*Hypothèses!$C$6 -> 1071943.1 | H6: =G6/SUM($G$4:$G$22)*(Hypothèses!$C$90+2*Hypothèses!$C$91)*Hypothèses!$C$6 -> 31817.418 | I6: =G6+H6 -> 1103760.5 | J6: =Hypothèses!$C$18 -> 0.1 | K6: =Hypothèses!$C$20+Hypothèses!$C$21+Hypothèses!$C$22+Hypothèses!$C$23 -> 0.0245 | L6: =I6*(J6+K6) -> 137418.18 | M6: =I6+L6 -> 1241178.7 | N6: https://www.pccomponentes.fr/sony-fe-24-70-mm-f28-gm-ii
A7: Flash Profoto B10X | B7: Studio | C7: 2 | D7: 1996.5 | E7: TTC | F7: =IF(E7="TTC",D7/(1+Hypothèses!$C$7),D7) -> 1663.75 | G7: =C7*F7*Hypothèses!$C$6 -> 2182696.9 | H7: =G7/SUM($G$4:$G$22)*(Hypothèses!$C$90+2*Hypothèses!$C$91)*Hypothèses!$C$6 -> 64786.817 | I7: =G7+H7 -> 2247483.7 | J7: =Hypothèses!$C$18 -> 0.1 | K7: =Hypothèses!$C$20+Hypothèses!$C$21+Hypothèses!$C$22+Hypothèses!$C$23 -> 0.0245 | L7: =I7*(J7+K7) -> 279811.72 | M7: =I7+L7 -> 2527295.5 | N7: https://profoto.com/bg/fr/shop/products/lights/monolights/profoto-b10x-us
A8: Flash Godox AD600 Pro II | B8: Studio | C8: 2 | D8: 899.95 | E8: TTC | F8: =IF(E8="TTC",D8/(1+Hypothèses!$C$7),D8) -> 749.95833 | G8: =C8*F8*Hypothèses!$C$6 -> 983880.84 | H8: =G8/SUM($G$4:$G$22)*(Hypothèses!$C$90+2*Hypothèses!$C$91)*Hypothèses!$C$6 -> 29203.554 | I8: =G8+H8 -> 1013084.4 | J8: =Hypothèses!$C$18 -> 0.1 | K8: =Hypothèses!$C$20+Hypothèses!$C$21+Hypothèses!$C$22+Hypothèses!$C$23 -> 0.0245 | L8: =I8*(J8+K8) -> 126129.01 | M8: =I8+L8 -> 1139213.4 | N8: https://center.lv/en/sony/Cameras-Camcorders-and-Optics/Flashes-lights/Flashes-and-accessories/External-flashes/10494-AD600Pro-II-All-in-One-Outdoor-Flash
A9: Projecteur LED Aputure LS 600d Pro | B9: Studio | C9: 1 | D9: 1850 | E9: HT | F9: =IF(E9="TTC",D9/(1+Hypothèses!$C$7),D9) -> 1850 | G9: =C9*F9*Hypothèses!$C$6 -> 1213520.4 | H9: =G9/SUM($G$4:$G$22)*(Hypothèses!$C$90+2*Hypothèses!$C$91)*Hypothèses!$C$6 -> 36019.718 | I9: =G9+H9 -> 1249540.2 | J9: =Hypothèses!$C$18 -> 0.1 | K9: =Hypothèses!$C$20+Hypothèses!$C$21+Hypothèses!$C$22+Hypothèses!$C$23 -> 0.0245 | L9: =I9*(J9+K9) -> 155567.75 | M9: =I9+L9 -> 1405107.9 | N9: https://avned.nl/merken/aputure/daglicht_5600k
A10: Stabilisateur DJI RS 4 | B10: Studio | C10: 1 | D10: 509 | E10: TTC | F10: =IF(E10="TTC",D10/(1+Hypothèses!$C$7),D10) -> 424.16667 | G10: =C10*F10*Hypothèses!$C$6 -> 278235.09 | H10: =G10/SUM($G$4:$G$22)*(Hypothèses!$C$90+2*Hypothèses!$C$91)*Hypothèses!$C$6 -> 8258.575 | I10: =G10+H10 -> 286493.67 | J10: =Hypothèses!$C$18 -> 0.1 | K10: =Hypothèses!$C$20+Hypothèses!$C$21+Hypothèses!$C$22+Hypothèses!$C$23 -> 0.0245 | L10: =I10*(J10+K10) -> 35668.462 | M10: =I10+L10 -> 322162.13 | N10: https://kulturegeek.fr/comparateur/produit/stabilisateur-dji-rs-4-7306
A11: Mac Studio M4 Max (retouche) | B11: Studio | C11: 1 | D11: 2649 | E11: TTC | F11: =IF(E11="TTC",D11/(1+Hypothèses!$C$7),D11) -> 2207.5 | G11: =C11*F11*Hypothèses!$C$6 -> 1448025.1 | H11: =G11/SUM($G$4:$G$22)*(Hypothèses!$C$90+2*Hypothèses!$C$91)*Hypothèses!$C$6 -> 42980.285 | I11: =G11+H11 -> 1491005.4 | J11: =Hypothèses!$C$18 -> 0.1 | K11: =Hypothèses!$C$20+Hypothèses!$C$21+Hypothèses!$C$22+Hypothèses!$C$23 -> 0.0245 | L11: =I11*(J11+K11) -> 185630.17 | M11: =I11+L11 -> 1676635.5 | N11: https://consomac.fr/news-22278-le-prix-du-mac-studio-2025-baisse-de-200.html
A12: Écran étalonné BenQ SW272U | B12: Studio | C12: 2 | D12: 1324.495 | E12: TTC | F12: =IF(E12="TTC",D12/(1+Hypothèses!$C$7),D12) -> 1103.7458 | G12: =C12*F12*Hypothèses!$C$6 -> 1448019.6 | H12: =G12/SUM($G$4:$G$22)*(Hypothèses!$C$90+2*Hypothèses!$C$91)*Hypothèses!$C$6 -> 42980.123 | I12: =G12+H12 -> 1490999.7 | J12: =Hypothèses!$C$18 -> 0.1 | K12: =Hypothèses!$C$20+Hypothèses!$C$21+Hypothèses!$C$22+Hypothèses!$C$23 -> 0.0245 | L12: =I12*(J12+K12) -> 185629.47 | M12: =I12+L12 -> 1676629.2 | N12: https://www.topachat.com/pages/detail2_cat_est_peripheriques_puis_rubrique_est_w_moni_puis_ref_est_in20019521.html
A13: MacBook Pro 14 M5 (postes de bureau) | B13: Informatique | C13: 14 | D13: 2099 | E13: TTC | F13: =IF(E13="TTC",D13/(1+Hypothèses!$C$7),D13) -> 1749.1667 | G13: =C13*F13*Hypothèses!$C$6 -> 16063294 | H13: =G13/SUM($G$4:$G$22)*(Hypothèses!$C$90+2*Hypothèses!$C$91)*Hypothèses!$C$6 -> 476790.74 | I13: =G13+H13 -> 16540084 | J13: =Hypothèses!$C$18 -> 0.1 | K13: =Hypothèses!$C$20+Hypothèses!$C$21+Hypothèses!$C$22+Hypothèses!$C$23 -> 0.0245 | L13: =I13*(J13+K13) -> 2059240.5 | M13: =I13+L13 -> 18599325 | N13: https://www.iphon.fr/?p=219249
A14: NAS Synology DS923+ | B14: Informatique | C14: 1 | D14: 707.775 | E14: TTC | F14: =IF(E14="TTC",D14/(1+Hypothèses!$C$7),D14) -> 589.8125 | G14: =C14*F14*Hypothèses!$C$6 -> 386891.64 | H14: =G14/SUM($G$4:$G$22)*(Hypothèses!$C$90+2*Hypothèses!$C$91)*Hypothèses!$C$6 -> 11483.719 | I14: =G14+H14 -> 398375.36 | J14: =Hypothèses!$C$18 -> 0.1 | K14: =Hypothèses!$C$20+Hypothèses!$C$21+Hypothèses!$C$22+Hypothèses!$C$23 -> 0.0245 | L14: =I14*(J14+K14) -> 49597.732 | M14: =I14+L14 -> 447973.09 | N14: https://www.mac4ever.com/mac/174138-synology-lance-le-nas-4-baies-ds923
A15: Passerelle Ubiquiti UniFi Dream Machine Pro | B15: Informatique | C15: 1 | D15: 464.475 | E15: TTC | F15: =IF(E15="TTC",D15/(1+Hypothèses!$C$7),D15) -> 387.0625 | G15: =C15*F15*Hypothèses!$C$6 -> 253896.36 | H15: =G15/SUM($G$4:$G$22)*(Hypothèses!$C$90+2*Hypothèses!$C$91)*Hypothèses!$C$6 -> 7536.1525 | I15: =G15+H15 -> 261432.51 | J15: =Hypothèses!$C$18 -> 0.1 | K15: =Hypothèses!$C$20+Hypothèses!$C$21+Hypothèses!$C$22+Hypothèses!$C$23 -> 0.0245 | L15: =I15*(J15+K15) -> 32548.347 | M15: =I15+L15 -> 293980.86 | N15: https://www.comparateur-gamer.fr/prix/ubiquiti-unifi-dream-machine-pro-817882027373
... A18: Contrôle d'accès (par porte) | B18: Sécurité | C18: 8 | D18: 500 | E18: HT | F18: =IF(E18="TTC",D18/(1+Hypothèses!$C$7),D18) -> 500 | G18: =C18*F18*Hypothèses!$C$6 -> 2623828 | H18: =G18/SUM($G$4:$G$22)*(Hypothèses!$C$90+2*Hypothèses!$C$91)*Hypothèses!$C$6 -> 77880.472 | I18: =G18+H18 -> 2701708.5 | J18: =Hypothèses!$C$18 -> 0.1 | K18: =Hypothèses!$C$20+Hypothèses!$C$21+Hypothèses!$C$22+Hypothèses!$C$23 -> 0.0245 | L18: =I18*(J18+K18) -> 336362.7 | M18: =I18+L18 -> 3038071.2 | N18: https://www.companeo.com/securite-electronique/FAQ/prix-controle-acces-entreprise
A19: Fauteuil Steelcase Gesture | B19: Mobilier | C19: 30 | D19: 1274 | E19: TTC | F19: =IF(E19="TTC",D19/(1+Hypothèses!$C$7),D19) -> 1061.6667 | G19: =C19*F19*Hypothèses!$C$6 -> 20892230 | H19: =G19/SUM($G$4:$G$22)*(Hypothèses!$C$90+2*Hypothèses!$C$91)*Hypothèses!$C$6 -> 620123.26 | I19: =G19+H19 -> 21512354 | J19: =Hypothèses!$C$19 -> 0.2 | K19: =Hypothèses!$C$20+Hypothèses!$C$21+Hypothèses!$C$22+Hypothèses!$C$23 -> 0.0245 | L19: =I19*(J19+K19) -> 4829523.4 | M19: =I19+L19 -> 26341877 | N19: https://www.comparateur-gamer.fr/prix/steelcase-gesture-chaise-de-bureau-ergonomique-avec-3760345221368
A20: Bureau professionnel 160 x 80 | B20: Mobilier | C20: 20 | D20: 382.815 | E20: HT | F20: =IF(E20="TTC",D20/(1+Hypothèses!$C$7),D20) -> 382.815 | G20: =C20*F20*Hypothèses!$C$6 -> 5022203.6 | H20: =G20/SUM($G$4:$G$22)*(Hypothèses!$C$90+2*Hypothèses!$C$91)*Hypothèses!$C$6 -> 149069.06 | I20: =G20+H20 -> 5171272.6 | J20: =Hypothèses!$C$19 -> 0.2 | K20: =Hypothèses!$C$20+Hypothèses!$C$21+Hypothèses!$C$22+Hypothèses!$C$23 -> 0.0245 | L20: =I20*(J20+K20) -> 1160950.7 | M20: =I20+L20 -> 6332223.4 | N20: https://www.hellopro.fr/mt-international-bureau-droit-l160xp80-plateau-chene-brut-et-pieds-u-noir-2015734-10255905-produit.html
A21: Banque d'accueil 2 postes | B21: Mobilier | C21: 1 | D21: 3003.345 | E21: HT | F21: =IF(E21="TTC",D21/(1+Hypothèses!$C$7),D21) -> 3003.345 | G21: =C21*F21*Hypothèses!$C$6 -> 1970065.2 | H21: =G21/SUM($G$4:$G$22)*(Hypothèses!$C$90+2*Hypothèses!$C$91)*Hypothèses!$C$6 -> 58475.481 | I21: =G21+H21 -> 2028540.7 | J21: =Hypothèses!$C$19 -> 0.2 | K21: =Hypothèses!$C$20+Hypothèses!$C$21+Hypothèses!$C$22+Hypothèses!$C$23 -> 0.0245 | L21: =I21*(J21+K21) -> 455407.38 | M21: =I21+L21 -> 2483948 | N21: https://www.hellopro.fr/banque-d-accueil-z2-pour-deux-personnes-avec-acces-bas-officity-orange-blanc-466-2001557-19222535-produit.html
A22: Groupe électrogène triphasé 10-60 kVA | B22: Énergie | C22: 1 | D22: 9000 | E22: HT | F22: =IF(E22="TTC",D22/(1+Hypothèses!$C$7),D22) -> 9000 | G22: =C22*F22*Hypothèses!$C$6 -> 5903613 | H22: =G22/SUM($G$4:$G$22)*(Hypothèses!$C$90+2*Hypothèses!$C$91)*Hypothèses!$C$6 -> 175231.06 | I22: =G22+H22 -> 6078844.1 | J22: =Hypothèses!$C$18 -> 0.1 | K22: =Hypothèses!$C$20+Hypothèses!$C$21+Hypothèses!$C$22+Hypothèses!$C$23 -> 0.0245 | L22: =I22*(J22+K22) -> 756816.09 | M22: =I22+L22 -> 6835660.1 | N22: https://conseils.hellopro.fr/guide-des-prix-des-groupes-electrogenes-1159.html
A23: Commissionnaire en douane (frais de dossier) | M23: =Hypothèses!$C$92 -> 25000
A24: COÛT RENDU YAOUNDÉ (hors transport Douala → Yaoundé : sur devis) | G24: =SUM(G4:G22) -> 67292933 | H24: =SUM(H4:H22) -> 1997389.1 | L24: =SUM(L4:L22) -> 11497862 | M24: =SUM(M4:M23) -> 80813184
A25: Prix catalogue équivalent TTC (pour mémoire) | G25: =SUMPRODUCT(C4:C22,F4:F22)*(1+Hypothèses!$C$7)*Hypothèses!$C$6 -> 80751520
A26: TVA camerounaise à l'import (19,25 %), récupérable au régime du réel | M26: =SUM(I4:I22,L4:L22)*Hypothèses!$C$12 -> 15551725

Sheet Flotte
A1: Flotte (achetée au Cameroun : droits déjà inclus dans le prix local)
A3: Véhicule | B3: Nombre | C3: Prix unitaire (FCFA) | D3: Investissement (FCFA) | E3: Durée (ans) | F3: Amortissement / mois (FCFA)
A4: Motos de livraison 125-150 cm³ | B4: =Hypothèses!$C$96 -> 8 | C4: =Hypothèses!$C$93 -> 544500 | D4: =B4*C4 -> 4356000 | E4: =Hypothèses!$C$119 -> 3 | F4: =D4/E4/12 -> 121000
A5: Utilitaire Toyota Hiace | B5: =Hypothèses!$C$97 -> 1 | C5: =Hypothèses!$C$94 -> 12500000 | D5: =B5*C5 -> 12500000 | E5: =Hypothèses!$C$120 -> 5 | F5: =D5/E5/12 -> 208333.33
A6: Véhicule de service Toyota Hilux | B6: =Hypothèses!$C$98 -> 1 | C6: =Hypothèses!$C$95 -> 16681700 | D6: =B6*C6 -> 16681700 | E6: =Hypothèses!$C$121 -> 5 | F6: =D6/E6/12 -> 278028.33
A7: Total flotte | D7: =SUM(D4:D6) -> 33537700 | F7: =SUM(F4:F6) -> 607361.67

Sheet Fonctionnement
A1: Coûts mensuels : fonctionnement Cameroun, amortissements, siège France
A3: Poste | B3: Montant mensuel (FCFA) | C3: Calcul
A4: Masse salariale Yaoundé (chargée) | B4: ='Masse salariale'!$H$22 -> 8924711.2 | C4: feuille Masse salariale
A5: Gardiennage | B5: ='Masse salariale'!$H$23 -> 598500 | C5: 4,2 ETP × prix société
A6: Électricité ENEO | B6: =Hypothèses!$C$107*Hypothèses!$C$106 -> 594000 | C6: kWh × tarif
A7: Internet professionnel | B7: =Hypothèses!$C$109*Hypothèses!$C$108 -> 65000 | C7: 2 lignes
A8: Licences Adobe | B8: =Hypothèses!$C$111*Hypothèses!$C$110*Hypothèses!$C$6 -> 157567.43 | C8: 3 licences
A9: Carburant motos | B9: =Hypothèses!$C$96*Hypothèses!$C$102*Hypothèses!$C$103*Hypothèses!$C$50*Hypothèses!$C$101/100*Hypothèses!$C$99 -> 570286.08 | C9: motos × livraisons × km × L/100 km × prix
A10: Carburant utilitaire | B10: =Hypothèses!$C$104*Hypothèses!$C$105/100*Hypothèses!$C$100 -> 165600 | C10: km × L/100 km × gasoil
A11: Taxe foncière | B11: =('Maison mère Yaoundé'!$E$18+'Maison mère Yaoundé'!$E$16)*Hypothèses!$C$27/12 -> 30187.5 | C11: 0,1 % de la valeur, mensualisée
A12: Total fonctionnement Cameroun | B12: =SUM(B4:B11) -> 11105852
A14: Amortissement bâtiment (construction + permis) | B14: =('Maison mère Yaoundé'!$E$16+'Maison mère Yaoundé'!$E$21)/Hypothèses!$C$113/12 -> 1129937.5
A15: Amortissement clôture | B15: ='Maison mère Yaoundé'!$E$22/Hypothèses!$C$114/12 -> 147118.1
A16: Amortissement matériel studio | B16: =SUMIF('Équipements importés'!$B$4:$B$22,"Studio",'Équipements importés'!$M$4:$M$22)/Hypothèses!$C$115/12 -> 368469.68
A17: Amortissement informatique et impression | B17: =(SUMIF('Équipements importés'!$B$4:$B$22,"Informatique",'Équipements importés'!$M$4:$M$22)+SUMIF('Équipements importés'!$B$4:$B$22,"Impression",'Équipements importés'!$M$4:$M$22))/Hypothèses!$C$115/12 -> 619355.71
A18: Amortissement sécurité | B18: =SUMIF('Équipements importés'!$B$4:$B$22,"Sécurité",'Équipements importés'!$M$4:$M$22)/Hypothèses!$C$117/12 -> 53879.348
A19: Amortissement mobilier | B19: =SUMIF('Équipements importés'!$B$4:$B$22,"Mobilier",'Équipements importés'!$M$4:$M$22)/Hypothèses!$C$116/12 -> 292983.74
A20: Amortissement groupe électrogène | B20: =SUMIF('Équipements importés'!$B$4:$B$22,"Énergie",'Équipements importés'!$M$4:$M$22)/Hypothèses!$C$118/12 -> 113927.67
A21: Amortissement motos | B21: =Flotte!$F$4 -> 121000
A22: Amortissement utilitaire | B22: =Flotte!$F$5 -> 208333.33
A23: Amortissement véhicule de service | B23: =Flotte!$F$6 -> 278028.33
A24: Total amortissements | B24: =SUM(B14:B23) -> 3333033.4
A26: Siège France : salaires chargés | B26: ='Masse salariale'!$G$29/12*Hypothèses!$C$6 -> 8869694.7
A27: Siège France : loyer | B27: =Hypothèses!$C$77*Hypothèses!$C$76/12*Hypothèses!$C$6 -> 706793.67
A28: Siège France : expert-comptable | B28: =Hypothèses!$C$78/12*Hypothèses!$C$6 -> 273315.42
A29: Siège France : RC Pro | B29: =Hypothèses!$C$79/12*Hypothèses!$C$6 -> 169455.56
A30: Siège France : banque | B30: =Hypothèses!$C$80*Hypothèses!$C$6 -> 19350.732
A31: Total siège France | B31: =SUM(B26:B30) -> 10038610
A33: Postes non chiffrés faute de source publique fiable (provisions, sur devis) :
A34: • Assurances (bâtiment, flotte, RC) : devis assureurs agréés
A35: • Équipements et véhicules des hubs classiques
A36: • Raccordement moyenne tension ENEO si la puissance l'exige
A37: • Entretien des motos et de l'utilitaire, pièces
A38: • Caméras de vidéosurveillance (aucun prix européen fiable trouvé)
A39: • Parking pavé, VRD, forage, raccordements ENEO et CAMWATER
A40: • Frais portuaires à Kribi et transport du conteneur Kribi → Yaoundé
A41: • Fonds et accessoires de studio, consommables d'impression
A42: • Hébergement web, logiciels métiers, eau, CFE France
A43: • Budget marketing (décision de gestion, pas un prix)

Sheet Prix
A1: Prix calculés à partir des coûts complets
A3: 1. LIVRAISON INTRA-YAOUNDÉ | B3: Valeur | C3: Calcul / repère
A4: Livraisons par moto et par mois | B4: =Hypothèses!$C$102*Hypothèses!$C$50 -> 312
A5: Capacité de la flotte (livraisons / mois) | B5: =Hypothèses!$C$96*Prix!$B$4 -> 2496
A6: Coursier par livraison | B6: ='Masse salariale'!$G$8/Prix!$B$4 -> 431.11111 | C6: coût chargé ÷ livraisons
A7: Amortissement moto par livraison | B7: =Hypothèses!$C$93/Hypothèses!$C$119/12/Prix!$B$4 -> 48.477564
A8: Carburant par livraison | B8: =Hypothèses!$C$103*Hypothèses!$C$101/100*Hypothèses!$C$99 -> 228.48
A9: Part du bâtiment occupée par le hub (selon son coût) | B9: =Fonctionnement!$B$14*('Maison mère Yaoundé'!$F$4+'Maison mère Yaoundé'!$F$5) -> 365630.06
A10: Manutention hub par colis (équipe + locaux) | B10: =(('Masse salariale'!$H$5+'Masse salariale'!$H$6+'Masse salariale'!$H$7)+Prix!$B$9)/Prix!$B$5 -> 803.94517
A11: COÛT DE REVIENT D'UNE LIVRAISON | B11: =Prix!$B$6+Prix!$B$7+Prix!$B$8+Prix!$B$10 -> 1512.0138
A12: Prix plancher HT (coût + marge) | B12: =Prix!$B$11*(1+Hypothèses!$C$123) -> 1814.4166
A13: PRIX PLANCHER TTC | B13: =Prix!$B$12*(1+Hypothèses!$C$12) -> 2163.6918 | C13: marché : 1 500 à 2 500 FCFA la course (Cameroon Tribune)
A14: Prix conseillé TTC | B14: =Hypothèses!$C$137 -> 2500 | C14: haut du marché : couvre assurance et entretien à chiffrer
A16: 2. STUDIO PREMIUM | B16: Valeur | C16: Calcul / repère
A17: Équipe studio (photographe, vidéaste, ½ graphiste) | B17: ='Masse salariale'!$H$13+'Masse salariale'!$H$14+0.5*'Masse salariale'!$H$15 -> 652136.88
A18: Part du bâtiment occupée par le studio (selon son coût) | B18: =Fonctionnement!$B$14*'Maison mère Yaoundé'!$F$6 -> 256644.17
A19: Amortissement du matériel studio importé | B19: =Fonctionnement!$B$16 -> 368469.68
A20: Électricité du studio | B20: =Fonctionnement!$B$6*Hypothèses!$C$129 -> 148500
A21: Licences logicielles | B21: =Fonctionnement!$B$8 -> 157567.43
A22: COÛT MENSUEL COMPLET DU STUDIO | B22: =Prix!$B$17+Prix!$B$18+Prix!$B$19+Prix!$B$20+Prix!$B$21 -> 1583318.2
A23: Heures facturables par mois | B23: =Hypothèses!$C$126*Hypothèses!$C$124*Hypothèses!$C$125 -> 92.4
A24: COÛT D'UNE HEURE DE STUDIO | B24: =Prix!$B$22/Prix!$B$23 -> 17135.478
A25: Starter : heures (5 produits en packshot fond blanc, retouchés + fiches) | B25: =5/Hypothèses!$C$127 -> 0.625
A26: Starter : coût de revient | B26: =Prix!$B$25*Prix!$B$24 -> 10709.674
A27: Starter : prix d'équilibre TTC (coût + TVA, sans marge) | B27: =Prix!$B$26*(1+Hypothèses!$C$12) -> 12771.286
A28: Starter : PRIX PLANCHER TTC (coût + marge + TVA) | B28: =Prix!$B$26*(1+Hypothèses!$C$123)*(1+Hypothèses!$C$12) -> 15325.543
A29: Starter : repère marché (bas de fourchette) | B29: =5*Hypothèses!$C$130 -> 25000
A30: Starter : PRIX CONSEILLÉ TTC = max(marché, plancher arrondi à 5 000) | B30: =MAX(Prix!$B$29,ROUNDUP(Prix!$B$28/5000,0)*5000) -> 25000
A31: Boost : heures (5 packshots + 5 lifestyle + 1 flyer + 1 short) | B31: =5/Hypothèses!$C$127+5/Hypothèses!$C$128+1 -> 3.2916667
A32: Boost : coût de revient | B32: =Prix!$B$31*Prix!$B$24 -> 56404.282
A33: Boost : prix d'équilibre TTC (coût + TVA, sans marge) | B33: =Prix!$B$32*(1+Hypothèses!$C$12) -> 67262.106
A34: Boost : PRIX PLANCHER TTC (coût + marge + TVA) | B34: =Prix!$B$32*(1+Hypothèses!$C$123)*(1+Hypothèses!$C$12) -> 80714.527
A35: Boost : repère marché (bas de fourchette) | B35: =5*Hypothèses!$C$130+5*Hypothèses!$C$131+Hypothèses!$C$132 -> 90000
A36: Boost : PRIX CONSEILLÉ TTC = max(marché, plancher arrondi à 5 000) | B36: =MAX(Prix!$B$35,ROUNDUP(Prix!$B$34/5000,0)*5000) -> 90000
A37: Business : heures (20 packshots + 10 lifestyle + mini-branding + 3 shorts) | B37: =20/Hypothèses!$C$127+10/Hypothèses!$C$128+4 -> 9.8333333
A38: Business : coût de revient | B38: =Prix!$B$37*Prix!$B$24 -> 168498.87
A39: Business : prix d'équilibre TTC (coût + TVA, sans marge) | B39: =Prix!$B$38*(1+Hypothèses!$C$12) -> 200934.9
A40: Business : PRIX PLANCHER TTC (coût + marge + TVA) | B40: =Prix!$B$38*(1+Hypothèses!$C$123)*(1+Hypothèses!$C$12) -> 241121.88
A41: Business : repère marché (bas de fourchette) | B41: =20*Hypothèses!$C$130+10*Hypothèses!$C$131+3*Hypothèses!$C$132 -> 245000
A42: Business : PRIX CONSEILLÉ TTC = max(marché, plancher arrondi à 5 000) | B42: =MAX(Prix!$B$41,ROUNDUP(Prix!$B$40/5000,0)*5000) -> 245000
A44: 3. COMMISSION ET SEUILS DE RENTABILITÉ | B44: Valeur | C44: Calcul / repère
A45: Commission par commande (HT) | B45: =Hypothèses!$C$133*Hypothèses!$C$135 -> 2775
A46: Frais mobile money (panier + livraison TTC) | B46: =Hypothèses!$C$134*(Hypothèses!$C$133+Prix!$B$13) -> 330.61907
A47: Marge sur la livraison (au prix plancher, par prudence) | B47: =(Prix!$B$12-Prix!$B$11) -> 302.40277 | C47: l'écart jusqu'au prix conseillé est réservé à l'assurance et à l'entretien
A48: Patente (sur le CA HT de la filiale) | B48: =Hypothèses!$C$11*(Prix!$B$45+Prix!$B$12) -> 12.988049
A49: Minimum de perception (2,2 % du CA HT) | B49: =Hypothèses!$C$10*(Prix!$B$45+Prix!$B$12) -> 100.96717
A50: CONTRIBUTION NETTE PAR COMMANDE | B50: =Prix!$B$45-Prix!$B$46+Prix!$B$47-Prix!$B$48-Prix!$B$49 -> 2632.8285
A51: Charges fixes de la filiale (hors livraison et studio) | B51: =Fonctionnement!$B$12-'Masse salariale'!$H$8-('Masse salariale'!$H$5+'Masse salariale'!$H$6+'Masse salariale'!$H$7)-Prix!$B$17-Prix!$B$20-Prix!$B$21-Fonctionnement!$B$9+Fonctionnement!$B$24-Fonctionnement!$B$21-Prix!$B$19-Prix!$B$18-Prix!$B$9 -> 9081581
A52: Siège France (coût mensuel) | B52: =Fonctionnement!$B$31 -> 10038610
A53: Frais de siège à facturer (siège au coût, retenue 7,5 % perdue) | B53: =Fonctionnement!$B$31/(1-Hypothèses!$C$15) -> 10852551
A54: Facteur après IS (frais déductibles à 2,5 % seulement) | B54: =1-Hypothèses!$C$9*(1-Hypothèses!$C$17) -> 0.731875
A55: SEUIL FILIALE SEULE (siège France financé par levée de fonds) | B55: =Prix!$B$51/Prix!$B$50 -> 3449.3629
A56: SEUIL GROUPE APRÈS IMPÔTS (siège financé par les frais de siège) | B56: =MAX(((Prix!$B$53/Prix!$B$54+Prix!$B$51)/(Prix!$B$50+Prix!$B$49)),((Prix!$B$53+Prix!$B$51)/Prix!$B$50)) -> 8746.0828
A57: Volume d'affaires au seuil groupe (GMV / mois) | B57: =Prix!$B$56*Hypothèses!$C$133 -> 1.6180253e+08
A58: Motos nécessaires au seuil groupe | B58: =ROUNDUP(Prix!$B$56/Prix!$B$4,0) -> 29
A59: Marge mensuelle du studio aux prix conseillés | B59: =((Prix!$B$30+Prix!$B$36+Prix!$B$42)/(1+Hypothèses!$C$12)/(Prix!$B$25+Prix!$B$31+Prix!$B$37))*Prix!$B$23*(1-Hypothèses!$C$11-Hypothèses!$C$10)-Prix!$B$22 -> 394988.97
A60: Seuil groupe avec la marge du studio | B60: =MAX((Prix!$B$53/Prix!$B$54+Prix!$B$51-Prix!$B$59)/(Prix!$B$50+Prix!$B$49),(Prix!$B$53+Prix!$B$51-Prix!$B$59)/Prix!$B$50) -> 8601.599
A62: 4. ABONNEMENT VENDEUR PREMIUM | B62: Valeur | C62: Calcul / repère
A63: Coût d'accompagnement par vendeur et par mois | B63: ='Masse salariale'!$G$12/Hypothèses!$C$136 -> 6694.4583
A64: PRIX PLANCHER TTC / mois | B64: =Prix!$B$63*(1+Hypothèses!$C$123)*(1+Hypothèses!$C$12) -> 9579.7699
A65: Prix conseillé TTC / mois | B65: =Hypothèses!$C$138 -> 10000

Sheet Fiscalité
A1: Remonter 100 FCFA de bénéfice camerounais vers la France : quatre cas
A3: Étape | B3: Dividendes (droit commun) | C3: Dividendes (PME) | D3: Frais de siège, siège au coût | E3: Frais de siège, siège imposé à 25 %
A4: Bénéfice avant impôt au Cameroun | B4: =100 -> 100 | C4: =100 -> 100 | D4: =100 -> 100 | E4: =100 -> 100
A5: IS Cameroun | B5: =B4*Hypothèses!$C$9 -> 27.5 | C5: =C4*Hypothèses!$C$9 -> 27.5 | D5: =D4*Hypothèses!$C$9*(1-Hypothèses!$C$17) -> 26.8125 | E5: =E4*Hypothèses!$C$9*(1-Hypothèses!$C$17) -> 26.8125
A6: Montant versé à la France | B6: =B4-B5 -> 72.5 | C6: =C4-C5 -> 72.5 | D6: =D4-D5 -> 73.1875 | E6: =E4-E5 -> 73.1875
A7: Retenue à la source au Cameroun | B7: =B6*Hypothèses!$C$13 -> 10.875 | C7: =C6*Hypothèses!$C$14*1.1 -> 7.975 | D7: =D6*Hypothèses!$C$15 -> 5.4890625 | E7: =E6*Hypothèses!$C$15 -> 5.4890625
A8: Impôt France | B8: =B6*Hypothèses!$C$40*Hypothèses!$C$39 -> 0.90625 | C8: =C6*Hypothèses!$C$40*Hypothèses!$C$39 -> 0.90625 | D8: =0 -> 0 | E8: =MAX(0,E6*Hypothèses!$C$39-E7) -> 12.807813
A9: NET DISPONIBLE EN FRANCE | B9: =B6-B7-B8 -> 60.71875 | C9: =C6-C7-C8 -> 63.61875 | D9: =D6-D7-D8 -> 67.698437 | E9: =E6-E7-E8 -> 54.890625
A11: Frais de siège : déductibles au Cameroun dans la limite de 2,5 % du bénéfice ; retenue de 7,5 % pour l'assistance technique documentée (15 % de TSR sinon) ; TVA camerounaise de 19,25 % autoliquidée par la filiale (déductible). Siège au coût : pas d'IS français, la retenue est perdue. Siège imposé : IS français à 25 % sous déduction de la retenue. À valider par un fiscaliste.

Sheet Hubs classiques
A1: Hubs classiques — terrain, bâtiment et clôture (hors équipements)
A3: Élément | B3: Hub S (sans studio) | C3: Hub M (studio compact)
A4: Stockage (m²) | B4: 250 | C4: 350
A5: Bureau du gestionnaire (m²) | B5: 15 | C5: 15
A6: Accueil et retrait (m²) | B6: 25 | C6: 30
A7: Sanitaires (m²) | B7: 15 | C7: 20
A8: Studio compact haut standing (m²) | B8: 0 | C8: 40
A9: Surface du terrain (m²) | B9: 600 | C9: 1000
A10: Surface de plancher (avec 15 % de circulations) | B10: =SUM(B4:B7)*(1+Hypothèses!$C$84)+B8 -> 350.75 | C10: =SUM(C4:C7)*(1+Hypothèses!$C$84)+C8 -> 517.25
A11: Construction (FCFA) | B11: =SUM(B4:B7)*(1+Hypothèses!$C$84)*Hypothèses!$C$82+B8*Hypothèses!$C$83 -> 52612500 | C11: =SUM(C4:C7)*(1+Hypothèses!$C$84)*Hypothèses!$C$82+C8*Hypothèses!$C$83 -> 86187500
A12: Terrain (FCFA) | B12: =B9*Hypothèses!$C$88 -> 36000000 | C12: =C9*Hypothèses!$C$88 -> 60000000
A13: Droits, conservation, notaire, permis (FCFA) | B13: =B12*(Hypothèses!$C$24+Hypothèses!$C$25)+MIN(B12,Hypothèses!$C$29)*Hypothèses!$C$33+MAX(0,MIN(B12,Hypothèses!$C$30)-Hypothèses!$C$29)*Hypothèses!$C$34+MAX(0,MIN(B12,Hypothèses!$C$31)-Hypothèses!$C$30)*Hypothèses!$C$35+MAX(0,MIN(B12,Hypothèses!$C$32)-Hypothèses!$C$31)*Hypothèses!$C$36+MAX(0,B12-Hypothèses!$C$32)*Hypothèses!$C$37+B11*Hypothèses!$C$26 -> 3683625 | C13: =C12*(Hypothèses!$C$24+Hypothèses!$C$25)+MIN(C12,Hypothèses!$C$29)*Hypothèses!$C$33+MAX(0,MIN(C12,Hypothèses!$C$30)-Hypothèses!$C$29)*Hypothèses!$C$34+MAX(0,MIN(C12,Hypothèses!$C$31)-Hypothèses!$C$30)*Hypothèses!$C$35+MAX(0,MIN(C12,Hypothèses!$C$32)-Hypothèses!$C$31)*Hypothèses!$C$36+MAX(0,C12-Hypothèses!$C$32)*Hypothèses!$C$37+C11*Hypothèses!$C$26 -> 5854375
A14: Clôture HT (FCFA) | B14: =4*SQRT(B9)*Hypothèses!$C$87/(1+Hypothèses!$C$12) -> 17297485 | C14: =4*SQRT(C9)*Hypothèses!$C$87/(1+Hypothèses!$C$12) -> 22330957
A15: INVESTISSEMENT TERRAIN + BÂTIMENT + CLÔTURE (FCFA) | B15: =B11+B12+B13+B14 -> 1.0959361e+08 | C15: =C11+C12+C13+C14 -> 1.7437283e+08

Sheet Sources
A1: Base de données sourcée (recherche web, octobre 2026)
A3: Thème | B3: Clé | C3: Libellé | D3: Bas | E3: Haut | F3: Unité | G3: Date | H3: Confiance | I3: Source | J3: URL | K3: Note
A4: fisc_cm | B4: is_taux_normal | C4: Impôt sur les sociétés, taux normal (CAC de 10 % compris) | D4: 33 | E4: 33 | F4: % | G4: 2025-2026 (CGI art. 17) | H4: high | I4: DGI Cameroun : Fiche technique A/s Impôt sur les Sociétés (IS) | J4: https://www.impots.cm/sites/default/files/documents/ok%20FT%20IS%20ok.pdf | K4: Fiche DGI : « Le taux applicable au Cameroun en matière d'impôt sur les sociétés est de 30% (article 17 (1) du CGI) », majoré de 10 % de centimes additionnels communaux, soit 33 %. PwC Worldwide Tax Summaries (revue d'août 2026) donne 33 % pour un CA supérieur à 3 milliards XAF (https://taxsummaries.pwc.com/Republic-of-Cameroon/Corporate/Taxes-on-corporate-income). La LF 2026 (loi n° 2025/012 du 17/12/2025) ne modifie pas ce taux. Chiffres repris des extraits du moteur de recherche : la page n'a pas pu être ouverte directement (réseau bloqué).
A5: fisc_cm | B5: is_taux_reduit_pme | C5: IS, taux réduit pour un chiffre d'affaires ≤ 3 milliards FCFA (CAC compris) | D5: 27.5 | E5: 27.5 | F5: % | G5: 2025-2026 | H5: high | I5: DGI Cameroun : Fiche technique A/s Impôt sur les Sociétés (IS) | J5: https://www.impots.cm/sites/default/files/documents/ok%20FT%20IS%20ok.pdf | K5: Fiche DGI : « ... et de 25% pour les contribuables réalisant un chiffre d'affaires égal ou inférieur à 3 milliards ». Avec 10 % de CAC, on obtient 27,5 %, confirmé par PwC (« smaller companies that meet statutory criteria pay 27.5% ») et par cga3s.com. Seuil : 3 000 000 000 FCFA, soit environ 4 573 471 EUR. D'anciennes pages du MINFI (35 %) et de Wikipédia (28 %) sont dépassées.
A6: fisc_cm | B6: is_acompte_minimum_perception | C6: Acompte mensuel d'IS / minimum de perception, régime du réel (CAC compris) | D6: 2.2 | E6: 2.2 | F6: % du CA mensuel | G6: 2025-2026 (CGI art. 21) | H6: medium | I6: DGI Cameroun : Fiche technique IS ; LeFisk (commentaire de la fiche DGI) | J6: https://www.impots.cm/sites/default/files/documents/ok%20FT%20IS%20ok.pdf | K6: Fiche DGI : « les acomptes mensuels d'IS sont calculés par application du taux de 2% sur le chiffre d'affaires mensuel des entreprises du régime du réel, majoré des CAC (article 21 du CGI) », soit 2,2 %. LeFisk (https://lefisk.cm/blog/impot-sur-les-societes-cameroun-fiche-dgi-taux-acomptes-pdf) précise que le minimum de perception de 2,2 % du CA reste dû même en cas de perte. Wikipédia (Fiscalité du Cameroun) donne 5,5 % CAC compris pour le régime simplifié. Le paiement se fait au plus tard le 15 du mois suivant.
A7: fisc_cm | B7: seuil_regime_reel | C7: Seuil de chiffre d'affaires HT au-delà duquel le régime du réel s'applique | D7: 50000000 | E7: 50000000 | F7: FCFA | G7: 2025-2026 | H7: medium | I7: LeFisk : Fiscalité, TVA (guide DGI) | J7: https://lefisk.cm/fiscalite/tva | K7: « toute entreprise dont le CA annuel dépasse 50 millions FCFA (régime réel) ». franco.wiki (Fiscalité du Cameroun) indique le même seuil, applicable de plein droit aux professions libérales. Cela représente environ 76 224 EUR. Le régime du réel entraîne l'assujettissement à la TVA.
A8: fisc_cm | B8: tva_taux_general | C8: TVA, taux général (17,5 % + CAC de 10 %) | D8: 19.25 | E8: 19.25 | F8: % | G8: 2025-2026 | H8: high | I8: DGI Cameroun : Fiche TVA | J8: https://impots.cm/sites/default/files/documents/FICHE%20TVA.pdf | K8: Fiche DGI : « Taux général : 19,25 % (soit un taux de 17,5 % majoré des centimes additionnels communaux de 10 %). Taux zéro : 0 % (applicable aux exportations) ». PwC confirme 19,25 %. Commerce électronique : la LF 2020 (art. 127) soumet à la TVA de 19,25 % les ventes de biens et services réalisées via des plateformes nationales ou étrangères, ainsi que les commissions des opérateurs de plateformes (Financial Afrik, 23/09/2020). La TVA à l'import se calcule au même taux.
A9: fisc_cm | B9: patente_cime | C9: Patente, moyennes entreprises (CIME) : taux sur le CA de l'exercice précédent | D9: 0.283 | E9: 0.283 | F9: % du CA | G9: 2017 (barème non reconfirmé pour 2025-2026) | H9: medium | I9: Deloitte Avocats : Cameroun, brèves juridiques et fiscales 1er trimestre 2017 | J9: https://blog.avocats.deloitte.fr/cameroun-breves-juridiques-fiscales-1er-trimestre-2017/ | K9: Deloitte : 0,283 % du CA du dernier exercice clos pour les moyennes entreprises, avec un minimum de 141 500 FCFA (≈ 215,7 EUR) et un maximum de 4 500 000 FCFA (≈ 6 860 EUR). Le formulaire officiel de la DGI (https://www.impots.cm/uploads/I-PL-TVA-IR.pdf) indique « Taux PATENTE : CDI = 0,494% ; CIME = 0,283% ; DGE = 0,159% ». La patente totale ajoute la taxe de développement local, les CAC et la redevance audiovisuelle.
A10: fisc_cm | B10: patente_dge_cdi | C10: Patente : fourchette des taux DGE (grandes entreprises) et CDI (petites entreprises) | D10: 0.159 | E10: 0.494 | F10: % du CA | G10: 2017-2025 | H10: medium | I10: Formulaire de déclaration DGI (I-PL-TVA-IR) | J10: https://www.impots.cm/uploads/I-PL-TVA-IR.pdf | K10: DGE : 0,159 %, avec un minimum de 5 M FCFA et un maximum de 2,5 Mds FCFA selon des portails commerciaux secondaires (Lloyds Bank Trade, Bank of Scotland Trade : https://www.lloydsbanktrade.com/en/market-potential/cameroon/taxes). CDI : 0,494 %, entre 50 000 et 140 000 FCFA (Deloitte 2017). Les mêmes portails indiquent que les entreprises nouvellement créées sont exonérées de patente la première année d'activité.
A11: fisc_cm | B11: ircm_dividendes_droit_commun | C11: IRCM (retenue sur dividendes), taux de droit commun CAC compris, résidents et non-résidents | D11: 16.5 | E11: 16.5 | F11: % | G11: Déc. 2025 | H11: high | I11: PwC Worldwide Tax Summaries : Cameroon, Withholding taxes | J11: https://taxsummaries.pwc.com/republic-of-cameroon/corporate/withholding-taxes | K11: PwC : « total WHT of 16.5% applies to dividends paid to both Cameroon residents and non-residents », soit 15 % + 10 % de CAC. Le taux peut être réduit par une convention. Pour une mère française, la convention de 1976 plafonne la retenue à 15 % (voir l'item conv_fr_cm_dividendes).
A12: fisc_cm | B12: ircm_dividendes_pme | C12: IRCM sur les dividendes distribués par les PME (LF 2025, art. 70 bis CGI), hors CAC | D12: 10 | E12: 10 | F12: % | G12: Depuis le 1/1/2025 (loi n° 2024/013 du 23/12/2024) | H12: medium | I12: MINFI : Exposé des mesures fiscales, lancement du budget 2025 | J12: https://minfi.gov.cm/wp-content/uploads/2025/01/Expose_Meesures_Fiscales_lancement_du_budget_2025_Fr.pdf | K12: Le tableau du MINFI indique « IRCM sur les dividendes des PME 15% → 10%, Article 70 bis du CGI ». Selon Cameroon Tribune (interview), le taux de 10 % s'entend hors CAC, et la charge globale sur les dividendes des PME passe de 39,46 % à 35,48 %. Afrique Sur 7 situe le seuil à un CA ≤ 3 Mds FCFA, mais le texte officiel n'a pas été vu pour ce point. Le taux reste de 15 % (16,5 % CAC compris) pour les grandes entreprises.
A13: fisc_cm | B13: ircm_interets | C13: Retenue à la source sur les intérêts d'emprunts étrangers (IRCM, CAC compris) | D13: 16.5 | E13: 16.5 | F13: % | G13: Déc. 2025 | H13: medium | I13: PwC Worldwide Tax Summaries : Cameroon, Withholding taxes | J13: https://taxsummaries.pwc.com/republic-of-cameroon/corporate/withholding-taxes | K13: PwC : « Interest from foreign loans is subject to 16.5% WHT ». Ce taux s'appliquerait à un prêt d'associé consenti par la SAS française à la filiale camerounaise. Le plafond prévu par la convention franco-camerounaise pour les intérêts n'a pas pu être confirmé (voir les lacunes).
A14: fisc_cm | B14: tsr_non_residents | C14: Taxe Spéciale sur le Revenu (TSR) : retenue sur prestations et redevances payées à des non-résidents | D14: 15 | E14: 15 | F14: % du montant brut | G14: 2025-2026 | H14: high | I14: MINFI : Régime fiscal des marchés publics | J14: https://minfi.gov.cm/marches-publics/ | K14: MINFI : la TSR est « à la charge de l'entreprise n'ayant pas un domicile fiscal au Cameroun, mais qui réalise des prestations diverses. Elle est retenue à la source », au taux de « 15% sur le montant brut des redevances et rémunérations servies, y compris la TSR elle-même ». PwC : « Royalties paid to non-residents are subject to a 15% WHT (the 10% surcharge is not applicable) ». Pour une entreprise française, ce taux est ramené à 7,5 % sur l'assistance technique, financière et comptable (voir l'item conv_fr_cm_assistance_technique).
A15: fisc_cm | B15: conv_fr_cm_assistance_technique | C15: Convention France-Cameroun : plafond de retenue sur études et assistance technique, financière ou comptable (frais de management) | D15: 7.5 | E15: 7.5 | F15: % du montant brut | G15: Avenant du 28/10/1999, en vigueur le 1/1/2003, applicable aux paiements depuis le 1/1/1998 | H15: high | I15: Assemblée nationale : rapport n° 35 (12e législature) sur l'avenant à la convention fiscale franco-camerounaise | J15: https://www.assemblee-nationale.fr/12/pdf/rapports/r0035.pdf | K15: « L'Etat de la source peut ainsi à nouveau imposer les rémunérations pour études, assistance technique, financière ou comptable, mais à un taux au plus égal à 7,5 % du montant brut de ces rémunérations ». La France accorde un crédit d'impôt dans cette limite. Le BOFiP (https://bofip.impots.gouv.fr/node/320966) précise l'application aux montants payés depuis le 1/1/1998 et l'entrée en vigueur au 1/1/2003. Les autres prestations restent à 15 % (droit commun TSR).
... A68: fisc_fr | B68: ras_assistance_technique_convention | C68: Plafond de retenue à la source camerounaise sur les rémunérations d'études, d'assistance technique, financière ou comptable facturées par la mère française (management fees) | D68: 7.5 | E68: 7.5 | F68: % du montant brut | G68: Avenant du 28/10/1999 (rétroactif au 01/01/1998), en vigueur en 2026 | H68: high | I68: Rapport Assemblée nationale n° 35 (XIIe législature) sur l'avenant à la convention fiscale France-Cameroun | J68: https://www.assemblee-nationale.fr/12/pdf/rapports/r0035.pdf | K68: L'article 4 de l'avenant de 1999 permet au Cameroun d'imposer ces rémunérations, avec une retenue plafonnée à 7,5 % (contre 15 % dans la version initiale). La France accorde un crédit d'impôt correspondant aux retenues opérées au Cameroun, dans la limite de 7,5 %. Confirmé par CMS (https://cms.law/en/fra/legal-updates/cameroun-ce-qu-il-faut-savoir-pour-s-implanter-et-exporter) et par le Sénat (https://www.senat.fr/leg/pjl00-181.html). Contrairement aux dividendes, ces fees sont imposables en France, donc le crédit d'impôt est utilisable.
A69: fisc_fr | B69: credit_impot_convention_plafond | C69: Crédit d'impôt conventionnel France-Cameroun : plafonnement à l'impôt dû dans l'État de résidence sur le même revenu | F69: mécanisme (crédit = impôt étranger, plafonné à l'impôt national dû sur ce revenu) | G69: Convention du 21/10/1976 modifiée (1994, 1999, CML 2017) | H69: medium | I69: Convention fiscale franco-camerounaise (DGI Cameroun, impots.cm) | J69: https://www.impots.cm/sites/default/files/documents/Convention-franco-camerounaise.pdf | K69: Le texte prévoit que l'impôt perçu dans l'État de la source « ouvre droit à un crédit d'impôt. Ce crédit correspond au montant de l'impôt […] perçu mais ne peut excéder le montant de l'impôt […] exigible sur ces revenus ». Le Cameroun a retenu l'option C de l'article 5 de la CML pour l'élimination des doubles impositions (OCDE). Version consolidée intégrant la CML : impots.gouv.fr (convention-avec-le-cameroun-modifiee-par-la-cml.pdf). Convention en vigueur depuis le 19 juillet 1978.
A70: fisc_fr | B70: prix_transfert_seuil_documentation | C70: Prix de transfert : seuil de l'obligation de documentation complète (article L13 AA LPF) | D70: 150000000 | E70: 150000000 | F70: EUR de CA HT ou d'actif brut | G70: Exercices ouverts depuis le 01/01/2024 | H70: high | I70: Loi de finances pour 2024 : les prix de transfert, objet de toutes les attentions (Deloitte Avocats) | J70: https://blog.avocats.deloitte.fr/loi-de-finances-pour-2024-les-prix-de-transfert-objet-de-toutes-les-attentions/ | K70: L'article 116 de la LF 2024 abaisse le seuil de 400 M€ à 150 M€ de CA HT ou d'actif brut. Amende minimale pour défaut de documentation portée à 50 000 € par exercice (article 1735 ter du CGI, Leyton). La déclaration simplifiée 2257-SD s'impose dès 50 M€ (article 223 quinquies B du CGI). ALQAVYA reste sous ces seuils, mais l'article 57 du CGI (prix de pleine concurrence) s'applique sans condition de taille : il faut justifier les management fees et refacturations à la filiale camerounaise. Le Cameroun impose aussi ses propres obligations (voir côté Cameroun).
A71: fisc_fr | B71: prix_transfert_2257_seuil | C71: Prix de transfert : seuil de la déclaration simplifiée 2257-SD | D71: 50000000 | E71: 50000000 | F71: EUR de CA HT ou d'actif brut | G71: 2024-2026 | H71: medium | I71: Documentation prix de transfert pour PME : kit pratique 2026 (Hayot Expertise) | J71: https://hayot-expertise.fr/blog/documentation-prix-de-transfert-pme-kit-pratique-2026 | K71: Seuil du formulaire 2257-SD (article 223 quinquies B du CGI) abaissé de 400 M€ à 50 M€. Dépôt dans les 6 mois suivant la liasse fiscale. Amende de 150 € en cas de défaut (article 1729 B du CGI). La déclaration pays par pays ne concerne que les groupes de plus de 750 M€ de CA consolidé.
A72: fisc_fr | B72: tva_services_filiale_hors_ue | C72: TVA française sur les prestations de services B2B facturées à la filiale camerounaise (preneur hors UE) | D72: 0 | E72: 0 | F72: % de TVA française (hors champ) | G72: 2026 | H72: high | I72: Comment facturer un client étranger : TVA intracommunautaire (Keobiz) | J72: https://www.keobiz.fr/fiches-pratiques/creation-dentreprise/comment-facturer-un-client-etranger-tva-intracommunautaire/ | K72: Une prestation B2B rendue à un preneur assujetti établi hors UE est localisée chez le preneur (article 259-1 du CGI) : pas de TVA française. Facture HT avec la mention « TVA non applicable – article 259-1 du CGI ». Pas de DES pour un client hors UE. C'est le client camerounais qui doit, le cas échéant, autoliquider la TVA camerounaise (19,25 %, voir côté Cameroun). La TVA française d'amont reste déductible.
A73: fisc_fr | B73: loyer_bureaux_paris_idf | C73: Loyer de bureaux en Île-de-France / Paris (moyenne seconde main IDF et loyer prime Paris QCA) | D73: 450 | E73: 1230 | F73: EUR HT HC/m²/an | G73: T1 2025 (moyenne IDF) / bilan 2025 (prime QCA) | H73: medium | I73: Étude marché locatif IDF T1 2025 (Newmark) ; Marché locatif bureaux Paris, bilan 2025 (JLL) | J73: https://nmrk.com/storage-nmrk/uploads/documents/02_ETUDE_March%C3%A9_Locatif_IDF.pdf | K73: Newmark/Immostat : loyer moyen seconde main en Île-de-France de 450 €/m²/an au T1 2025 (440 un an plus tôt). JLL, bilan 2025 (https://www.jll.com/fr-fr/newsroom/cp-marche-locatif-bureaux-paris-bilan-2025) : loyer prime QCA de 1 230 €/m²/an (+11 %), Paris 18/19/20 : 590 €, Paris 14/15 : 750 €. BNP Paribas RE (note DRIEAT S2 2025) : prime parisien de 1 250 €. Les mesures d'accompagnement atteignent environ 19 % à Paris. Pas de moyenne Paris hors QCA consolidée (voir gaps).
A74: fisc_fr | B74: loyer_bureaux_lyon | C74: Loyer moyen de bureaux à Lyon (seconde main et neuf) | D74: 198 | E74: 233 | F74: EUR HT HC/m²/an | G74: S1 2025 | H74: high | I74: Analyses du marché tertiaire lyonnais au S1 2025 (JLL / CECIM) | J74: https://www.jll.com/fr-fr/newsroom/lyon-chiffres-cecim-s1-2025 | K74: Loyer moyen de 198 € en seconde main et 233 € dans le neuf. Loyer prime : 380 €/m²/an. CBRE T4 2025 : prime Part-Dieu à 370 € pour le neuf, loyers globalement stables, vacance à 7,9 %. Loyers affichés sur BureauxLocaux : moyenne de 220 € (fourchette 108-446).
A75: fisc_fr | B75: loyer_bureaux_lille | C75: Loyer moyen de bureaux dans la métropole lilloise (seconde main et neuf) | D75: 163 | E75: 183 | F75: EUR HT HC/m²/an | G75: S1 2025 | H75: high | I75: Lille : JLL commente les chiffres ImmoStat du 1er semestre | J75: https://www.jll.com/fr-fr/newsroom/lille-jll-commente-les-chiffres-immostat-du-1er-semestre | K75: Loyers moyens de 183 €/m²/an dans le neuf et 163 €/m²/an en seconde main. CBRE, bilan 2025 : loyer prime QCA de 250 €, vacance à 7,5 %. Loyers affichés sur BureauxLocaux : moyenne de 205 €.
A76: fisc_fr | B76: loyer_bureaux_bordeaux | C76: Loyer moyen de bureaux à Bordeaux intra-muros (seconde main et neuf) | D76: 226 | E76: 255 | F76: EUR HT HC/m²/an | G76: 2025 | H76: medium | I76: Prix moyen m² des bureaux à louer à Bordeaux (Tourny Meyer) | J76: https://www.tournymeyer.fr/conseils/prix-location-bureaux-bordeaux/ | K76: Valeur locative moyenne à Bordeaux intra-muros : environ 255 € HT HC pour le neuf et 226 € pour la seconde main. CBRE T4 2025 : vacance d'environ 8 % sur la métropole, loyer prime QCA de 230 € selon l'extrait. Les données de l'observatoire OIEB/a'urba 2025 n'ont pas été consultées.
A77: fisc_fr | B77: loyer_bureaux_nantes | C77: Loyer de bureaux à Nantes (moyenne et prime) | D77: 173 | E77: 250 | F77: EUR HT HC/m²/an | G77: 2024 (moyenne) / T4 2025 (prime) | H77: medium | I77: Location de bureaux à Nantes : prix au m² (Arthur Loyd) ; CBRE Figures Bureaux Nantes T4 | J77: https://www.arthur-loyd.com/actualites/le-prix-des-bureaux-a-louer-a-nantes | K77: Arthur Loyd : loyer moyen de 173 € HT HC/m²/an sur 2024, fourchette de 230-300 € dans le neuf et 170-250 € en seconde main. CBRE T4 2025 : prime de 250 € (Euronantes, Île de Nantes, Centre), 140-190 € en périphérie. Loyers affichés sur BureauxLocaux (juin 2026) : moyenne de 193 €.
A78: fisc_fr | B78: loyer_bureaux_toulouse | C78: Loyer moyen affiché de bureaux à Toulouse | D78: 170 | E78: 170 | F78: EUR HT HC/m²/an | G78: 2026-07 | H78: low | I78: Prix affichés des bureaux Toulouse (BureauxLocaux) | J78: https://www.bureauxlocaux.com/prix-marche/bureaux/toulouse | K78: Loyer moyen affiché d'environ 170 € HT HC/m²/an (fourchette de 92 à 327), en hausse de 3,8 % sur un an. Il s'agit d'annonces, pas de loyers signés. Le CBRE T4 2025 Toulouse (demande placée de 125 700 m²) n'a pas pu être lu pour les loyers.
A79: fisc_fr | B79: coworking_bureau_prive_paris | C79: Bureau privatif en centre d'affaires ou coworking à Paris (1 personne) | D79: 400 | E79: 1100 | F79: EUR/mois | G79: 2026 | H79: medium | I79: Prix coworking (Cocowork) | J79: https://cocowork.fr/prix-coworking/ | K79: Paris : bureau fermé de 400 à 700 €/mois pour 1 personne, 600 à 1 200 € pour 2 personnes. Poste fixe en open space de 250 à 450 €/mois. WeWork : bureau privatif 1 personne de 700 à 1 100 €/mois, poste fixe de 450 à 650 €. Selon Cocowork, Lyon, Bordeaux et Nantes sont en moyenne environ 30 % moins chers que Paris. Ces prix incluent généralement charges, internet et accueil.
A80: fisc_fr | B80: coworking_bureau_prive_lyon | C80: Bureau privatif ou poste fermé en centre d'affaires à Lyon | D80: 288 | E80: 900 | F80: EUR HT/poste/mois | G80: 2026 | H80: medium | I80: Besoin d'un espace de travail à Lyon ? (Workin.space) ; Prestaburo Monplaisir Lyon 3 | J80: https://workin.space/fr/france/lyon | K80: Workin.space : la moitié des espaces lyonnais proposent un poste en bureau fermé sous 288 € HT/mois (médiane de 302 €/poste tout inclus). Exemple Prestaburo Lyon 3 (https://workin.space/coworking/france/lyon-69/lyon-3-69003/prestaburo-monplaisir) : poste fixe dès 280 € HT/mois, bureau privatif 2 personnes dès 790 € HT/mois. Wezoo : 450 à 900 €/poste/mois en serviced office (https://wezoo.com/insights/prix-location-bureau-lyon).
A81: fisc_fr | B81: assurance_rc_pro | C81: Prime annuelle d'assurance RC Pro pour une petite entreprise tech / numérique | D81: 200 | E81: 6000 | F81: EUR/an | G81: 2026 | H81: medium | I81: RC pro informatique : tarifs et garanties (Philtr) | J81: https://philtr.fr/responsabilite-civile-professionnelle/metier/informatique | K81: Philtr (prix moyens constatés) : 200 à 350 €/an pour un CA < 100 k€ avec 100 k€ de plafond, jusqu'à 5 000 à 6 000 €/an pour un CA < 3 M€ avec 3 M€ de plafond. Swim.legal (https://www.swim.legal/blog/assurance-entreprise-prix) : une TPE paie en moyenne 300 à 1 500 €/an pour la seule RC Pro. Coover : environ 200 €/an pour une start-up avec un plafond de 50 k€ (offre AIG à 199 €). Pour une marketplace avec filiale africaine, viser un plafond ≥ 1 M€, soit environ 1 000 à 3 000 €/an (interpolation dans le barème Philtr).
... A225: utilities_market | B225: groupe_electrogene_triphase_france | C225: Groupe électrogène triphasé 10 à 60 kVA : fourchette de prix d'achat en France (référence import) | D225: 3000 | E225: 15000 | F225: EUR | G225: 2025-2026 | H225: medium | I225: Hellopro : guide des prix des groupes électrogènes | J225: https://conseils.hellopro.fr/guide-des-prix-des-groupes-electrogenes-1159.html | K225: Environ 1,97 à 9,84 M FCFA à la parité 655,957. Le triphasé 400 V, le capotage insonorisé ou le démarrage automatique (ATS) ajoutent 20 à 40 % au prix à puissance égale. Exemple : un 20 kVA diesel Könner & Söhnen listé à 5 872 € sur Touslesprix (https://www.touslesprix.com/achat,groupe-electrogene-20-kva.html). Hors fret, douane et installation au Cameroun. Extrait de résultat de recherche.
A226: utilities_market | B226: groupe_electrogene_occasion_yaounde | C226: Groupe électrogène Genelec 13,5 kVA d'occasion, en panne : mise à prix d'une vente UE ECHO à Yaoundé | D226: 2000000 | F226: FCFA (prix minimum) | G226: 2026 | H226: medium | I226: Avis de vente UE ECHO : groupe électrogène | J226: https://www.eeas.europa.eu/sites/default/files/2026/documents/Avis%20de%20vente%20UE%20ECHO_Groupe%20%C3%A9lectrog%C3%A8ne.pdf | K226: Seul prix en FCFA trouvé au Cameroun pour un groupe électrogène : mise à prix minimale d'un groupe acheté en 2016 et hors service. Ne vaut pas prix de référence pour du neuf en 20 à 30 kVA. Extrait de résultat de recherche.
A227: utilities_market | B227: solaire_cout_installation_kw | C227: Solaire photovoltaïque : coût d'installation par kW (hypothèse de planification pour le Cameroun) | D227: 550000 | E227: 550000 | F227: FCFA/kW installé | G227: 2026 | H227: low | I227: Afrotools : calculateur de ROI solaire Cameroun | J227: https://afrotools.com/fr/tools/roi-solaire/cameroon/ | K227: Valeurs préchargées par le calculateur : 550 000 FCFA par kW installé, plus un budget batterie de 550 000 FCFA ; hypothèses de 70 FCFA/kWh pour l'électricité et de 730 FCFA/l pour le carburant. C'est une hypothèse de planification, pas un devis : le site recommande d'en demander un. Extrait de résultat de recherche.
A228: utilities_market | B228: carburant_gasoil_pompe | C228: Prix à la pompe du gasoil (pour le coût de fonctionnement d'un groupe) | D228: 828 | E228: 828 | F228: FCFA/litre | G228: depuis le 3 février 2024 | H228: medium | I228: Ecomatin : l'État prévoit une baisse de 94,2 % de la subvention des prix des carburants en 2025 | J228: https://ecomatin.net/cameroun-letat-prevoit-une-baisse-de-942-de-la-subvention-des-prix-des-carburants-en-2025 | K228: Hausse d'environ 15 % au 3/2/2024 : gasoil 828 FCFA/l (+108), super 840 FCFA/l (+110). Le gasoil est passé de 545 à 828 FCFA entre février 2023 et février 2024 (+52 %). Le PLF 2025 prévoyait de réduire fortement les subventions, mais une réintroduction de 254 Md FCFA est ensuite évoquée, donc le prix 2025-2026 n'est pas confirmé. Chiffres présents dans les extraits (Ecomatin, Journal du Cameroun, L'Essentiel de l'Éco) ; l'attribution exacte à l'un de ces sites reste à confirmer.
A229: utilities_market | B229: internet_camtel_fibre_entree_gamme | C229: Internet : fibre illimitée Camtel (Blue), entrée de gamme | D229: 25000 | F229: FCFA/mois (8 Mbps) | G229: 2026 | H229: low | I229: Temovision : Forfaits Internet au Cameroun 2026, qui est le moins cher ? | J229: https://temovision.com/fr/forfaits-internet-au-cameroun/ | K229: Citation de l'extrait : « La fibre optique illimitée de Camtel commence à 25 000 XAF pour 8 Mbps ». La source ne dit pas si l'offre est résidentielle ou professionnelle ; aucune offre pro à débit garanti n'a été trouvée. Extrait de résultat de recherche, page non récupérable.
A230: utilities_market | B230: internet_orange_illimite_30j | C230: Internet : forfait Orange Cameroun illimité 30 jours | D230: 25000 | F230: FCFA/30 jours (débit plafonné à 2-5 Mbps) | G230: 2026 | H230: low | I230: Temovision : Forfaits Internet au Cameroun 2026, qui est le moins cher ? | J230: https://temovision.com/fr/forfaits-internet-au-cameroun/ | K230: Forfait qui ne vise pas spécifiquement les entreprises. Ecomatin (article non daté) annonçait aussi une box Orange « Infinity » à partir de 14 900 FCFA/mois à Douala et Yaoundé : https://ecomatin.net/le-dg-dorange-repond-aux-sollicitations-des-camerounais-a-travers-une-offre-innovante. Extrait de résultat de recherche.
A231: utilities_market | B231: internet_box_adsl_fourchette | C231: Internet : box ADSL/fixe, fourchette de coût mensuel | D231: 20000 | E231: 45000 | F231: FCFA/mois | G231: non daté | H231: low | I231: Ecomatin : TIC, le Cameroun compte plus de 50 fournisseurs d'accès Internet en activité | J231: https://ecomatin.net/tic-le-cameroun-compte-plus-de-50-fournisseurs-dacces-internet-en-activite | K231: Étude citée par Ecomatin : le coût varie de 20 000 à 45 000 FCFA par mois selon les besoins de l'utilisateur. Date de l'article à vérifier. Extrait de résultat de recherche.
A232: utilities_market | B232: mtn_momo_collecte_api_officiel | C232: MTN MoMo Cameroun : frais de collecte du widget et de l'API Collections (barème officiel) | D232: 1 | E232: 1 | F232: % par transaction | G232: 2025-2026 (page MoMo API) | H232: medium | I232: MTN MoMo API : Cameroon Collections Widget Details | J232: https://momoapi.mtn.com/Cameroon_Widget_productDetails | K232: Extrait : « a fee of 1% shall be charged per transaction », négociable entre MTN Mobile Money Cameroon et le client. Voir aussi la page Collections : https://momoapi.mtn.com/Cameroon_Collection_productDetails. MTN a annoncé en mars 2026 des paiements marchands sans frais pour le client payeur (AllAfrica : https://fr.allafrica.com/stories/202603310593.html). Extrait de résultat de recherche.
A233: utilities_market | B233: mtn_momo_encaissement_marchand_estime | C233: MTN MoMo : commission d'encaissement marchand (estimations d'un blog) | D233: 1 | E233: 2 | F233: % par transaction | G233: 2026 | H233: low | I233: Kolonell : MTN MoMo merchant fees Cameroon 2026 | J233: https://kolonell.com/en/blog/mtn-momo-merchant-fees-cameroon-2026 | K233: Un même éditeur donne des chiffres incohérents selon ses articles : 1 %, 1,0-1,5 %, environ 1,6 %, 1,5-2 %. Plafond journalier cité : 5 000 000 FCFA. Ce sont des ordres de grandeur non officiels. Extrait de résultat de recherche.
A234: utilities_market | B234: orange_money_encaissement_marchand_estime | C234: Orange Money Cameroun : commission d'encaissement marchand (estimations d'un blog) | D234: 1 | E234: 1.8 | F234: % par transaction | G234: 2026 | H234: low | I234: Kolonell : coût réel d'encaissement Orange Money au Cameroun pour un commerçant (2026) | J234: https://kolonell.com/fr/blog/cout-reel-encaissement-orange-money-cameroun-commercant-2026 | K234: Chiffres cités par le même éditeur : 1,5 %, 1,0-1,7 % et environ 1,8 % côté marchand. Coût total cash-out compris estimé à environ 3,5 % (contre environ 3 % chez MTN). Aucun barème officiel Orange trouvé. Extrait de résultat de recherche.
A235: utilities_market | B235: mtn_momo_frais_retrait | C235: MTN MoMo : frais de retrait (cash-out des encaissements) | D235: 1 | E235: 1.5 | F235: % du montant (+4 FCFA de taxe via USSD) | G235: 2025 | H235: medium | I235: Digital Business Africa : les tarifs de retrait de MTN Mobile Money (MoMo) en 2025 | J235: https://www.digitalbusiness.africa/cameroun-les-tarifs-de-retrait-de-mtn-mobile-money-momo-en-2025/ | K235: 1 % via l'application MoMo pour les retraits supérieurs à 5 000 FCFA ; 1,5 % + 4 FCFA via *126#. Les dépôts sont gratuits. Extrait de résultat de recherche.
A236: utilities_market | B236: orange_money_frais_retrait | C236: Orange Money Cameroun : frais de retrait | D236: 1.5 | E236: 2 | F236: % du montant | G236: article antérieur à 2025 / barème 2022 | H236: low | I236: Ecomatin : Orange Cameroun abaisse ses tarifs mobile money et relève les plafonds de retrait | J236: https://ecomatin.net/mobile-money-orange-cameroun-abaisse-ses-tarifs-et-releve-les-plafonds-de-retrait | K236: Ecomatin : 1,5 % du montant, plafonné à 3 500 FCFA. Cameroon Tribune (harmonisation de 2022, https://cameroon-tribune.cm/article.html/47269/fr.html/details_2) : retrait à 2 % (minimum 50 F), transfert à 0,5 % plafonné à 500 F, dépôt gratuit. Ces barèmes sont peut-être obsolètes. Extrait de résultat de recherche.
A237: utilities_market | B237: taxe_etat_mobile_money | C237: Taxe de l'État sur les transferts et retraits mobile money | D237: 0.2 | E237: 0.2 | F237: % + 4 FCFA par transaction | G237: depuis janvier 2022 (forfait de 4 FCFA ajouté ensuite) | H237: medium | I237: Business in Cameroon : Cameroon's mobile money transactions rise almost fourfold in five years despite new taxes | J237: https://www.businessincameroon.com/finance/2110-15212-cameroon-s-mobile-money-transactions-rise-almost-fourfold-in-five-years-despite-new-taxes | K237: Taxe de 0,2 % sur les transferts et retraits via portefeuille mobile, complétée ensuite par un forfait de 4 FCFA par transaction, étendu aux banques et aux microfinances. Extrait de résultat de recherche.
A238: utilities_market | B238: cinetpay_frais_transaction | C238: CinetPay : frais de transaction marchand (Afrique francophone) | D238: 2.5 | E238: 3.5 | F238: % par transaction (hors frais de reversement) | G238: non daté | H238: low | I238: TechCabal (FR) : article sur CinetPay | J238: https://techcabal.com/fr/?p=179865 | K238: Frais de 2,5 à 3,5 % selon le pays et le moyen de paiement, plus des frais de reversement de 1,2 à 2 % avant le versement sur le compte bancaire ou mobile money. En Côte d'Ivoire, chiffres indicatifs 2026 de Kolonell (https://kolonell.com/fr/blog/cinetpay-integration-tarifs-commissions-cote-ivoire-2026) : mobile money environ 3 % + 50 FCFA, carte environ 3,2 % + 100 FCFA, versement à J+2. Aucune grille officielle pour le Cameroun. Extrait de résultat de recherche.
A239: utilities_market | B239: jumia_commission_nigeria | C239: Jumia Nigeria : commission vendeur par catégorie | D239: 5 | E239: 20 | F239: % du prix de vente | G239: 2026 | H239: low | I239: Kolonell : Sell on Jumia vs own store, Nigeria 2026 | J239: https://kolonell.com/en/blog/sell-on-jumia-vs-own-store-nigeria-2026 | K239: Mode et accessoires 12-20 % ; beauté 12-18 % ; électronique 5-10 % ; maison et cuisine 10-15 % ; épicerie 8-12 %. Frais de manutention et de logistique en plus. Estimation d'un tiers, pas la grille officielle : la grille Jumia en vigueur au 15/01/2026 sur vendor.jumia.com n'était pas lisible. Attribution probable à cet article Kolonell. Extrait de résultat de recherche.
A240: utilities_market | B240: jumia_commission_senegal | C240: Jumia Sénégal : commission vendeur par catégorie (+ frais fixes par commande) | D240: 12 | E240: 22 | F240: % du prix de vente | G240: mai 2026 | H240: low | I240: Kolonell : marketplace locale vs Jumia au Sénégal (2026) | J240: https://kolonell.com/fr/blog/marketplace-local-vs-jumia-senegal-2026 | K240: Mode 18 %, beauté 22 %, électronique 12 %, maison et bureau 15 %, supermarché 14 %. Frais fixes de 800 à 1 500 FCFA par commande selon la catégorie. Jumia aurait fermé au Sénégal en 2024 puis rouvert fin 2025 en version allégée (4 catégories). Blog de consultant. Extrait de résultat de recherche.
A241: utilities_market | B241: jumia_take_rate_afrique_ouest | C241: Jumia : take rate e-commerce produits (Nigeria, Sénégal, Côte d'Ivoire) | D241: 12 | E241: 22 | F241: % du GMV | G241: 2026 | H241: low | I241: Kolonell : take rate des marketplaces en Afrique, modèles 2026 | J241: https://kolonell.com/fr/blog/take-rate-marketplace-afrique-modeles-2026 | K241: Seule fourchette couvrant la Côte d'Ivoire ; aucun barème officiel ivoirien trouvé. Pour le Kenya, seule source : un pitch deck Jumia non daté (mode 30 %, téléphones à partir de 5 %, https://www.slideshare.net/slideshow/jumia-marketplace-pitch/40861471), probablement obsolète. Extrait de résultat de recherche.
A242: utilities_market | B242: jumia_sortie_cameroun | C242: Jumia : arrêt de l'activité e-commerce au Cameroun | D242: 2019 | E242: 2019 | F242: année (18 novembre 2019) | G242: 18/11/2019 | H242: high | I242: Quartz : Jumia shuts down in Cameroon as African e-commerce struggles | J242: https://qz.com/africa/1751659/jumia-shuts-down-in-cameroon-as-african-e-commerce-struggles | K242: Portail transactionnel et bureaux fermés le 18/11/2019, modèle jugé « inadapté » à l'environnement local. Seul le site d'annonces deals.jumia.cm a été maintenu. Troisième départ après Cdiscount (2016) et Afrimarket (2019). Également rapporté par ITWeb, TechNext et Sagaci Research. Aucun retour de Jumia au Cameroun trouvé. Extrait de résultat de recherche.
... A259: web | B259: video_courte_produit | C259: Vidéo courte de produit (Douala / Yaoundé) | D259: 15000 | E259: 25000 | F259: FCFA par vidéo | G259: 2026 | H259: low | I259: Kolonell — catalogue produits boutique en ligne (Cameroun) | J259: https://kolonell.com/fr/blog/catalogue-produits-boutique-en-ligne-douala-yaounde-2026 | K259: Extrait de résultat de recherche : « vidéo courte de produit à 15 000-25 000 FCFA ». Bas de fourchette retenu comme repère de marché.
